{
  "generatedAt": "2026-05-20T16:14:49.257Z",
  "mode": "browser_roller",
  "cadence": {
    "targetRunsPerDay": 8,
    "targetHoursJst": [
      "every 3 hours"
    ],
    "postsPerSource": 3,
    "sourceLimit": 25,
    "lookbackDays": 60,
    "profilePostScanLimit": 24
  },
  "policy": {
    "sourceEligibility": "Only approved official Instagram sources from instagramPostInspection are eligible.",
    "collectionArchitecture": "Freshness lane opens the latest three posts/reels. If those posts are already known, or if the account has no observations yet, the backfill lane scrolls within the profile and opens the next unknown posts up to the configured per-source limit. Posts with a visible posted date older than the lookback window are skipped.",
    "savedFields": "post URL, shortcode, displayed/parsed posted date, classification, short summary, short quote, review status, decision note",
    "excludedFields": "passwords, cookies, session tokens, full captions, images, videos, comments, DMs, stories",
    "publication": "Never publish automatically. Browser observations can only become public after Admin candidate review approval."
  },
  "browserSession": {
    "state": "authenticated",
    "userDataDir": ".zac-browser/instagram",
    "headless": true,
    "checkedAt": "2026-05-20T16:14:54.769Z",
    "reason": null
  },
  "summary": {
    "sourcesQueued": 25,
    "sourcesVisited": 25,
    "sourcesSucceeded": 23,
    "sourcesFailed": 2,
    "sourcesDeferred": 0,
    "profilesWithNoRecentPosts": 0,
    "postsSeen": 322,
    "newPostsOpened": 69,
    "duplicatePostsSkipped": 253,
    "lookbackPostsSkipped": 13,
    "observedPosts": 69,
    "pendingPosts": 12,
    "ignoredPosts": 57,
    "calendarCandidates": 37
  },
  "inspections": [
    {
      "eventSourceId": "5992b14a-f6af-4bc0-a7a1-77efc68130e0",
      "handle": "dogwood_climbing_gym",
      "displayName": "DOGWOOD Climbing Gym 公式Instagram",
      "sourceUrl": "https://www.instagram.com/dogwood_climbing_gym/",
      "ok": false,
      "deferred": false,
      "posts": [],
      "postsSeen": 0,
      "newPostsOpened": 0,
      "duplicatePostsSkipped": 0,
      "lookbackPostsSkipped": 0,
      "inspectionMode": null,
      "lookbackCutoff": "2026-03-21T16:14:49.257Z",
      "noRecentPosts": false,
      "error": "profile_unavailable",
      "failureCategory": "profile_unavailable",
      "failureDetail": "Profile or post unavailable; status=200"
    },
    {
      "eventSourceId": "7061a581-458e-485a-8a88-b9c9adf269e1",
      "handle": "climb.vortex",
      "displayName": "ボルダリングジム Vortex（ボルテックス）",
      "sourceUrl": "https://www.instagram.com/climb.vortex/",
      "ok": false,
      "deferred": false,
      "posts": [],
      "postsSeen": 0,
      "newPostsOpened": 0,
      "duplicatePostsSkipped": 0,
      "lookbackPostsSkipped": 0,
      "inspectionMode": null,
      "lookbackCutoff": "2026-03-21T16:14:49.257Z",
      "noRecentPosts": false,
      "error": "checkpoint_required",
      "failureCategory": "checkpoint_required",
      "failureDetail": "Instagram checkpoint or challenge UI detected."
    },
    {
      "eventSourceId": "ae3bf68c-ef39-4336-8496-08ad3618b804",
      "handle": "basecamp_shinjuku",
      "displayName": "Urban Base Camp 新宿",
      "sourceUrl": "https://www.instagram.com/basecamp_shinjuku/",
      "ok": true,
      "deferred": false,
      "posts": [
        {
          "eventSourceId": "ae3bf68c-ef39-4336-8496-08ad3618b804",
          "handle": "basecamp_shinjuku",
          "displayName": "Urban Base Camp 新宿",
          "sourceUrl": "https://www.instagram.com/reel/DYjf7PuS3-r/",
          "sourceExternalId": "DYjf7PuS3-r",
          "sourcePostedAt": null,
          "classification": "notice",
          "title": "Urban Base Camp 新宿 2026/10/06 イベント",
          "summary": "Urban Base Camp 新宿の公式情報に基づく2026/10/06のイベント情報です。内容や参加条件は公式情報で確認してください。",
          "startsAt": "2026-10-06T01:00:00.000Z",
          "endsAt": "2026-10-06T02:00:00.000Z",
          "sourceQuote": "Urban Base Camp 新宿",
          "extractionConfidence": "0.40",
          "reviewStatus": "ignored",
          "decisionNote": "Browser roller found no calendar-worthy event signal in the visible post text."
        },
        {
          "eventSourceId": "ae3bf68c-ef39-4336-8496-08ad3618b804",
          "handle": "basecamp_shinjuku",
          "displayName": "Urban Base Camp 新宿",
          "sourceUrl": "https://www.instagram.com/reel/DYg7HaOyhgz/",
          "sourceExternalId": "DYg7HaOyhgz",
          "sourcePostedAt": null,
          "classification": "notice",
          "title": "Urban Base Camp 新宿 2026/10/06 イベント",
          "summary": "Urban Base Camp 新宿の公式情報に基づく2026/10/06のイベント情報です。内容や参加条件は公式情報で確認してください。",
          "startsAt": "2026-10-06T01:00:00.000Z",
          "endsAt": "2026-10-06T02:00:00.000Z",
          "sourceQuote": "Urban Base Camp 新宿",
          "extractionConfidence": "0.40",
          "reviewStatus": "ignored",
          "decisionNote": "Browser roller found no calendar-worthy event signal in the visible post text."
        },
        {
          "eventSourceId": "ae3bf68c-ef39-4336-8496-08ad3618b804",
          "handle": "basecamp_shinjuku",
          "displayName": "Urban Base Camp 新宿",
          "sourceUrl": "https://www.instagram.com/reel/DYeWX_MSYwh/",
          "sourceExternalId": "DYeWX_MSYwh",
          "sourcePostedAt": null,
          "classification": "notice",
          "title": "Urban Base Camp 新宿 2026/04/09 イベント",
          "summary": "Urban Base Camp 新宿の公式情報に基づく2026/04/09のイベント情報です。内容や参加条件は公式情報で確認してください。",
          "startsAt": "2026-04-09T01:00:00.000Z",
          "endsAt": "2026-04-09T02:00:00.000Z",
          "sourceQuote": "Urban Base Camp 新宿",
          "extractionConfidence": "0.40",
          "reviewStatus": "ignored",
          "decisionNote": "Browser roller found no calendar-worthy event signal in the visible post text."
        }
      ],
      "postsSeen": 11,
      "newPostsOpened": 3,
      "duplicatePostsSkipped": 8,
      "lookbackPostsSkipped": 0,
      "inspectionMode": "backfill",
      "lookbackCutoff": "2026-03-21T16:14:49.257Z",
      "noRecentPosts": false,
      "error": null,
      "failureCategory": null,
      "failureDetail": null
    },
    {
      "eventSourceId": "1c927437-7710-4318-9d77-e0e2104c9dc1",
      "handle": "bpump_ogikubo",
      "displayName": "B-PUMP OGIKUBO",
      "sourceUrl": "https://www.instagram.com/bpump_ogikubo/",
      "ok": true,
      "deferred": false,
      "posts": [
        {
          "eventSourceId": "1c927437-7710-4318-9d77-e0e2104c9dc1",
          "handle": "bpump_ogikubo",
          "displayName": "B-PUMP OGIKUBO",
          "sourceUrl": "https://www.instagram.com/p/DYjYCZckaCD/",
          "sourceExternalId": "DYjYCZckaCD",
          "sourcePostedAt": null,
          "classification": "competition",
          "title": "B-PUMP OGIKUBO  コンペ",
          "summary": "B-PUMP OGIKUBOの公式情報に基づくコンペ・大会情報です。開催日や申込方法は公式情報で確認してください。",
          "startsAt": null,
          "endsAt": null,
          "sourceQuote": "kiltergrips",
          "extractionConfidence": "0.55",
          "reviewStatus": "pending",
          "decisionNote": "B-PUMP OGIKUBOの公式Instagramからコンペ・大会候補を検出。日付候補は未確定。Adminで開催日、対象店舗、参加条件、申込要否を確認してください。根拠抜粋: kiltergrips"
        },
        {
          "eventSourceId": "1c927437-7710-4318-9d77-e0e2104c9dc1",
          "handle": "bpump_ogikubo",
          "displayName": "B-PUMP OGIKUBO",
          "sourceUrl": "https://www.instagram.com/p/DYW6IzPEvSb/",
          "sourceExternalId": "DYW6IzPEvSb",
          "sourcePostedAt": null,
          "classification": "route_set",
          "title": "B-PUMP OGIKUBO  セット",
          "summary": "B-PUMP OGIKUBOの公式情報に基づくセット・ホールド替え情報です。対象エリアや利用制限は公式情報で確認してください。",
          "startsAt": null,
          "endsAt": null,
          "sourceQuote": "bpump_ogikubo",
          "extractionConfidence": "0.55",
          "reviewStatus": "pending",
          "decisionNote": "B-PUMP OGIKUBOの公式Instagramからセット・ホールド替え候補を検出。日付候補は未確定。Adminで対象エリア、作業期間、利用制限を確認してください。根拠抜粋: bpump_ogikubo"
        },
        {
          "eventSourceId": "1c927437-7710-4318-9d77-e0e2104c9dc1",
          "handle": "bpump_ogikubo",
          "displayName": "B-PUMP OGIKUBO",
          "sourceUrl": "https://www.instagram.com/p/DYUTzRVklaO/",
          "sourceExternalId": "DYUTzRVklaO",
          "sourcePostedAt": null,
          "classification": "notice",
          "title": "B-PUMP OGIKUBO  イベント",
          "summary": "B-PUMP OGIKUBOの公式情報に基づくイベント情報です。内容や参加条件は公式情報で確認してください。",
          "startsAt": null,
          "endsAt": null,
          "sourceQuote": "bpump_ogikubo",
          "extractionConfidence": "0.40",
          "reviewStatus": "ignored",
          "decisionNote": "Browser roller found no calendar-worthy event signal in the visible post text."
        }
      ],
      "postsSeen": 12,
      "newPostsOpened": 3,
      "duplicatePostsSkipped": 9,
      "lookbackPostsSkipped": 0,
      "inspectionMode": "backfill",
      "lookbackCutoff": "2026-03-21T16:14:49.257Z",
      "noRecentPosts": false,
      "error": null,
      "failureCategory": null,
      "failureDetail": null
    },
    {
      "eventSourceId": "86b3a08a-8bae-454f-9eb0-241adab7b8ec",
      "handle": "bpumptokyo",
      "displayName": "B-PUMP Tokyo",
      "sourceUrl": "https://www.instagram.com/bpumptokyo/",
      "ok": true,
      "deferred": false,
      "posts": [
        {
          "eventSourceId": "86b3a08a-8bae-454f-9eb0-241adab7b8ec",
          "handle": "bpumptokyo",
          "displayName": "B-PUMP Tokyo",
          "sourceUrl": "https://www.instagram.com/p/DYg7G5VAWSr/",
          "sourceExternalId": "DYg7G5VAWSr",
          "sourcePostedAt": null,
          "classification": "route_set",
          "title": "B-PUMP Tokyo 2026/05/24 セット",
          "summary": "B-PUMP Tokyoの公式情報に基づく2026/05/24のセット・ホールド替え情報です。対象エリアや利用制限は公式情報で確認してください。",
          "startsAt": "2026-05-24T11:00:00.000Z",
          "endsAt": "2026-05-25T12:00:00.000Z",
          "sourceQuote": "bpumptokyo",
          "extractionConfidence": "0.72",
          "reviewStatus": "pending",
          "decisionNote": "B-PUMP Tokyoの公式Instagramからセット・ホールド替え候補を検出。日付候補は2026/05/24。Adminで対象エリア、作業期間、利用制限を確認してください。根拠抜粋: bpumptokyo"
        },
        {
          "eventSourceId": "86b3a08a-8bae-454f-9eb0-241adab7b8ec",
          "handle": "bpumptokyo",
          "displayName": "B-PUMP Tokyo",
          "sourceUrl": "https://www.instagram.com/reel/DYeWTMjTUeu/",
          "sourceExternalId": "DYeWTMjTUeu",
          "sourcePostedAt": null,
          "classification": "notice",
          "title": "B-PUMP Tokyo 2026/05/23 イベント",
          "summary": "B-PUMP Tokyoの公式情報に基づく2026/05/23のイベント情報です。内容や参加条件は公式情報で確認してください。",
          "startsAt": "2026-05-23T01:00:00.000Z",
          "endsAt": "2026-05-23T02:00:00.000Z",
          "sourceQuote": "bpumptokyo",
          "extractionConfidence": "0.40",
          "reviewStatus": "ignored",
          "decisionNote": "Browser roller found no calendar-worthy event signal in the visible post text."
        },
        {
          "eventSourceId": "86b3a08a-8bae-454f-9eb0-241adab7b8ec",
          "handle": "bpumptokyo",
          "displayName": "B-PUMP Tokyo",
          "sourceUrl": "https://www.instagram.com/p/DYZMy9xjsWi/",
          "sourceExternalId": "DYZMy9xjsWi",
          "sourcePostedAt": null,
          "classification": "route_set",
          "title": "B-PUMP Tokyo 2026/05/21 セット",
          "summary": "B-PUMP Tokyoの公式情報に基づく2026/05/21のセット・ホールド替え情報です。対象エリアや利用制限は公式情報で確認してください。",
          "startsAt": "2026-05-21T12:00:00.000Z",
          "endsAt": "2026-05-22T12:00:00.000Z",
          "sourceQuote": "bpumptokyo",
          "extractionConfidence": "0.72",
          "reviewStatus": "pending",
          "decisionNote": "B-PUMP Tokyoの公式Instagramからセット・ホールド替え候補を検出。日付候補は2026/05/21。Adminで対象エリア、作業期間、利用制限を確認してください。根拠抜粋: bpumptokyo"
        }
      ],
      "postsSeen": 12,
      "newPostsOpened": 3,
      "duplicatePostsSkipped": 9,
      "lookbackPostsSkipped": 0,
      "inspectionMode": "backfill",
      "lookbackCutoff": "2026-03-21T16:14:49.257Z",
      "noRecentPosts": false,
      "error": null,
      "failureCategory": null,
      "failureDetail": null
    },
    {
      "eventSourceId": "7046b655-8cd4-4087-a233-db5bb52aa729",
      "handle": "energyurawa",
      "displayName": "エナジークライミングジム浦和店公式Instagram",
      "sourceUrl": "https://www.instagram.com/energyurawa/",
      "ok": true,
      "deferred": false,
      "posts": [
        {
          "eventSourceId": "7046b655-8cd4-4087-a233-db5bb52aa729",
          "handle": "energyurawa",
          "displayName": "エナジークライミングジム浦和店公式Instagram",
          "sourceUrl": "https://www.instagram.com/p/DYMbCeilBrJ/",
          "sourceExternalId": "DYMbCeilBrJ",
          "sourcePostedAt": "2026-05-11T00:00:00.000Z",
          "classification": "recruit",
          "title": "エナジークライミングジム浦和店 2026/05/12 イベント",
          "summary": "エナジークライミングジム浦和店の公式情報に基づく2026/05/12のイベント情報です。内容や参加条件は公式情報で確認してください。",
          "startsAt": "2026-05-12T01:00:00.000Z",
          "endsAt": "2026-05-11T12:00:00.000Z",
          "sourceQuote": "energyurawa",
          "extractionConfidence": "0.40",
          "reviewStatus": "ignored",
          "decisionNote": "Recruiting post; tracked to avoid repeated inspection but not a public calendar item."
        },
        {
          "eventSourceId": "7046b655-8cd4-4087-a233-db5bb52aa729",
          "handle": "energyurawa",
          "displayName": "エナジークライミングジム浦和店公式Instagram",
          "sourceUrl": "https://www.instagram.com/reel/DYJE5wUipyE/",
          "sourceExternalId": "DYJE5wUipyE",
          "sourcePostedAt": null,
          "classification": "notice",
          "title": "エナジークライミングジム浦和店 2026/10/07 イベント",
          "summary": "エナジークライミングジム浦和店の公式情報に基づく2026/10/07のイベント情報です。内容や参加条件は公式情報で確認してください。",
          "startsAt": "2026-10-06T17:23:00.000Z",
          "endsAt": "2026-10-06T18:23:00.000Z",
          "sourceQuote": "energyurawa",
          "extractionConfidence": "0.40",
          "reviewStatus": "ignored",
          "decisionNote": "Browser roller found no calendar-worthy event signal in the visible post text."
        },
        {
          "eventSourceId": "7046b655-8cd4-4087-a233-db5bb52aa729",
          "handle": "energyurawa",
          "displayName": "エナジークライミングジム浦和店公式Instagram",
          "sourceUrl": "https://www.instagram.com/reel/DYBkZkEPhKm/",
          "sourceExternalId": "DYBkZkEPhKm",
          "sourcePostedAt": null,
          "classification": "notice",
          "title": "エナジークライミングジム浦和店 2026/09/08 イベント",
          "summary": "エナジークライミングジム浦和店の公式情報に基づく2026/09/08のイベント情報です。内容や参加条件は公式情報で確認してください。",
          "startsAt": "2026-09-08T01:00:00.000Z",
          "endsAt": "2026-09-08T02:00:00.000Z",
          "sourceQuote": "energyurawa",
          "extractionConfidence": "0.40",
          "reviewStatus": "ignored",
          "decisionNote": "Browser roller found no calendar-worthy event signal in the visible post text."
        }
      ],
      "postsSeen": 12,
      "newPostsOpened": 3,
      "duplicatePostsSkipped": 9,
      "lookbackPostsSkipped": 0,
      "inspectionMode": "backfill",
      "lookbackCutoff": "2026-03-21T16:14:49.257Z",
      "noRecentPosts": false,
      "error": null,
      "failureCategory": null,
      "failureDetail": null
    },
    {
      "eventSourceId": "8dd8d0fc-d295-40af-bd1c-a676b1d8ea4a",
      "handle": "be_born_climbing_gym",
      "displayName": "be_born_climbing_gym",
      "sourceUrl": "https://www.instagram.com/be_born_climbing_gym/",
      "ok": true,
      "deferred": false,
      "posts": [
        {
          "eventSourceId": "8dd8d0fc-d295-40af-bd1c-a676b1d8ea4a",
          "handle": "be_born_climbing_gym",
          "displayName": "be_born_climbing_gym",
          "sourceUrl": "https://www.instagram.com/p/DXwipQBE-l0/",
          "sourceExternalId": "DXwipQBE-l0",
          "sourcePostedAt": "2026-04-30T00:00:00.000Z",
          "classification": "opening_change",
          "title": "be_born_climbing_gym 2026/05/01 営業変更",
          "summary": "be_born_climbing_gymの公式情報に基づく2026/05/01の営業変更情報です。営業時間や営業影響は公式情報で確認してください。",
          "startsAt": "2026-05-01T01:00:00.000Z",
          "endsAt": "2026-05-01T02:00:00.000Z",
          "sourceQuote": "be_born_climbing_gym",
          "extractionConfidence": "0.72",
          "reviewStatus": "pending",
          "decisionNote": "be_born_climbing_gymの公式Instagramから営業時間・休業変更候補を検出。日付候補は2026/05/01。Adminで変更日、営業時間、休業/短縮営業の範囲を確認してください。根拠抜粋: be_born_climbing_gym"
        },
        {
          "eventSourceId": "8dd8d0fc-d295-40af-bd1c-a676b1d8ea4a",
          "handle": "be_born_climbing_gym",
          "displayName": "be_born_climbing_gym",
          "sourceUrl": "https://www.instagram.com/p/DXoRrkhkxXN/",
          "sourceExternalId": "DXoRrkhkxXN",
          "sourcePostedAt": "2026-05-01T00:00:00.000Z",
          "classification": "opening_change",
          "title": "be_born_climbing_gym 2026/04/29 営業変更",
          "summary": "be_born_climbing_gymの公式情報に基づく2026/04/29の営業変更情報です。営業時間や営業影響は公式情報で確認してください。",
          "startsAt": "2026-04-29T01:00:00.000Z",
          "endsAt": "2026-04-29T12:00:00.000Z",
          "sourceQuote": "be_born_climbing_gym",
          "extractionConfidence": "0.72",
          "reviewStatus": "pending",
          "decisionNote": "be_born_climbing_gymの公式Instagramから営業時間・休業変更候補を検出。日付候補は2026/04/29。Adminで変更日、営業時間、休業/短縮営業の範囲を確認してください。根拠抜粋: be_born_climbing_gym"
        },
        {
          "eventSourceId": "8dd8d0fc-d295-40af-bd1c-a676b1d8ea4a",
          "handle": "be_born_climbing_gym",
          "displayName": "be_born_climbing_gym",
          "sourceUrl": "https://www.instagram.com/p/DXk2K9tk4TE/",
          "sourceExternalId": "DXk2K9tk4TE",
          "sourcePostedAt": "2026-04-26T00:00:00.000Z",
          "classification": "event",
          "title": "be_born_climbing_gym  イベント",
          "summary": "be_born_climbing_gymの公式情報に基づくイベント情報です。内容や参加条件は公式情報で確認してください。",
          "startsAt": null,
          "endsAt": null,
          "sourceQuote": "be_born_climbing_gym",
          "extractionConfidence": "0.55",
          "reviewStatus": "pending",
          "decisionNote": "be_born_climbing_gymの公式Instagramからイベント候補を検出。日付候補は未確定。Adminで開催日、内容、参加条件を確認してください。根拠抜粋: be_born_climbing_gym"
        }
      ],
      "postsSeen": 12,
      "newPostsOpened": 3,
      "duplicatePostsSkipped": 9,
      "lookbackPostsSkipped": 0,
      "inspectionMode": "backfill",
      "lookbackCutoff": "2026-03-21T16:14:49.257Z",
      "noRecentPosts": false,
      "error": null,
      "failureCategory": null,
      "failureDetail": null
    },
    {
      "eventSourceId": "924eff10-8759-4291-8975-8c9afb0f9ace",
      "handle": "exciting_sancha",
      "displayName": "exciting_sancha",
      "sourceUrl": "https://www.instagram.com/exciting_sancha/",
      "ok": true,
      "deferred": false,
      "posts": [
        {
          "eventSourceId": "924eff10-8759-4291-8975-8c9afb0f9ace",
          "handle": "exciting_sancha",
          "displayName": "exciting_sancha",
          "sourceUrl": "https://www.instagram.com/p/DWdVSzpkX4T/",
          "sourceExternalId": "DWdVSzpkX4T",
          "sourcePostedAt": "2026-03-29T00:00:00.000Z",
          "classification": "notice",
          "title": "exciting_sancha 2026/03/29 イベント",
          "summary": "exciting_sanchaの公式情報に基づく2026/03/29のイベント情報です。内容や参加条件は公式情報で確認してください。",
          "startsAt": "2026-03-29T01:00:00.000Z",
          "endsAt": "2026-03-29T02:00:00.000Z",
          "sourceQuote": "exciting_sancha",
          "extractionConfidence": "0.40",
          "reviewStatus": "ignored",
          "decisionNote": "Browser roller found no calendar-worthy event signal in the visible post text."
        },
        {
          "eventSourceId": "924eff10-8759-4291-8975-8c9afb0f9ace",
          "handle": "exciting_sancha",
          "displayName": "exciting_sancha",
          "sourceUrl": "https://www.instagram.com/p/DVp-7H_kYTu/",
          "sourceExternalId": "DVp-7H_kYTu",
          "sourcePostedAt": "2026-03-09T00:00:00.000Z",
          "classification": "notice",
          "title": "exciting_sancha  イベント",
          "summary": "exciting_sanchaの公式情報に基づくイベント情報です。内容や参加条件は公式情報で確認してください。",
          "startsAt": null,
          "endsAt": null,
          "sourceQuote": "exciting_sancha",
          "extractionConfidence": "0.30",
          "reviewStatus": "ignored",
          "decisionNote": "Ignored by Instagram backfill lookback guard: visible posted date is older than 60 days."
        },
        {
          "eventSourceId": "924eff10-8759-4291-8975-8c9afb0f9ace",
          "handle": "exciting_sancha",
          "displayName": "exciting_sancha",
          "sourceUrl": "https://www.instagram.com/p/DVVUZSnEa5K/",
          "sourceExternalId": "DVVUZSnEa5K",
          "sourcePostedAt": "2026-03-01T00:00:00.000Z",
          "classification": "notice",
          "title": "exciting_sancha  イベント",
          "summary": "exciting_sanchaの公式情報に基づくイベント情報です。内容や参加条件は公式情報で確認してください。",
          "startsAt": null,
          "endsAt": null,
          "sourceQuote": "exciting_sancha",
          "extractionConfidence": "0.30",
          "reviewStatus": "ignored",
          "decisionNote": "Ignored by Instagram backfill lookback guard: visible posted date is older than 60 days."
        }
      ],
      "postsSeen": 24,
      "newPostsOpened": 3,
      "duplicatePostsSkipped": 21,
      "lookbackPostsSkipped": 2,
      "inspectionMode": "backfill",
      "lookbackCutoff": "2026-03-21T16:14:49.257Z",
      "noRecentPosts": false,
      "error": null,
      "failureCategory": null,
      "failureDetail": null
    },
    {
      "eventSourceId": "b2e46ff9-fa74-4413-9269-457f4a24775f",
      "handle": "noborock_takadanobaba",
      "displayName": "NOBOROCK 高田馬場店",
      "sourceUrl": "https://www.instagram.com/noborock_takadanobaba/",
      "ok": true,
      "deferred": false,
      "posts": [
        {
          "eventSourceId": "b2e46ff9-fa74-4413-9269-457f4a24775f",
          "handle": "noborock_takadanobaba",
          "displayName": "NOBOROCK 高田馬場店",
          "sourceUrl": "https://www.instagram.com/reel/DYjbh8RxWK5/",
          "sourceExternalId": "DYjbh8RxWK5",
          "sourcePostedAt": null,
          "classification": "notice",
          "title": "NOBOROCK 高田馬場店 2026/05/08 イベント",
          "summary": "NOBOROCK 高田馬場店の公式情報に基づく2026/05/08のイベント情報です。内容や参加条件は公式情報で確認してください。",
          "startsAt": "2026-05-08T01:00:00.000Z",
          "endsAt": "2026-05-08T02:00:00.000Z",
          "sourceQuote": "noborock_takadanobaba",
          "extractionConfidence": "0.40",
          "reviewStatus": "ignored",
          "decisionNote": "Browser roller found no calendar-worthy event signal in the visible post text."
        },
        {
          "eventSourceId": "b2e46ff9-fa74-4413-9269-457f4a24775f",
          "handle": "noborock_takadanobaba",
          "displayName": "NOBOROCK 高田馬場店",
          "sourceUrl": "https://www.instagram.com/reel/DYhSE7Iyy7d/",
          "sourceExternalId": "DYhSE7Iyy7d",
          "sourcePostedAt": null,
          "classification": "notice",
          "title": "NOBOROCK 高田馬場店  イベント",
          "summary": "NOBOROCK 高田馬場店の公式情報に基づくイベント情報です。内容や参加条件は公式情報で確認してください。",
          "startsAt": null,
          "endsAt": null,
          "sourceQuote": "noborock_shibuya",
          "extractionConfidence": "0.40",
          "reviewStatus": "ignored",
          "decisionNote": "Browser roller found no calendar-worthy event signal in the visible post text."
        },
        {
          "eventSourceId": "b2e46ff9-fa74-4413-9269-457f4a24775f",
          "handle": "noborock_takadanobaba",
          "displayName": "NOBOROCK 高田馬場店",
          "sourceUrl": "https://www.instagram.com/p/DYg6MV5R-Ah/",
          "sourceExternalId": "DYg6MV5R-Ah",
          "sourcePostedAt": null,
          "classification": "private_booking",
          "title": "NOBOROCK 高田馬場店 2026/05/25 貸切",
          "summary": "NOBOROCK 高田馬場店の公式情報に基づく2026/05/25の貸切・利用制限情報です。一般利用への影響は公式情報で確認してください。",
          "startsAt": "2026-05-25T01:00:00.000Z",
          "endsAt": "2026-05-25T02:00:00.000Z",
          "sourceQuote": "noborock_takadanobaba",
          "extractionConfidence": "0.72",
          "reviewStatus": "pending",
          "decisionNote": "NOBOROCK 高田馬場店の公式Instagramから貸切・利用制限候補を検出。日付候補は2026/05/25。Adminで貸切日時、一般利用への影響を確認してください。根拠抜粋: noborock_takadanobaba"
        }
      ],
      "postsSeen": 23,
      "newPostsOpened": 3,
      "duplicatePostsSkipped": 20,
      "lookbackPostsSkipped": 0,
      "inspectionMode": "backfill",
      "lookbackCutoff": "2026-03-21T16:14:49.257Z",
      "noRecentPosts": false,
      "error": null,
      "failureCategory": null,
      "failureDetail": null
    },
    {
      "eventSourceId": "29729a2e-530f-4bd6-a77f-f3d9a586f18e",
      "handle": "headrockcg",
      "displayName": "headrockcg",
      "sourceUrl": "https://www.instagram.com/headrockcg/",
      "ok": true,
      "deferred": false,
      "posts": [
        {
          "eventSourceId": "29729a2e-530f-4bd6-a77f-f3d9a586f18e",
          "handle": "headrockcg",
          "displayName": "headrockcg",
          "sourceUrl": "https://www.instagram.com/p/DYjyWIHk51H/",
          "sourceExternalId": "DYjyWIHk51H",
          "sourcePostedAt": null,
          "classification": "opening_change",
          "title": "headrockcg  営業変更",
          "summary": "headrockcgの公式情報に基づく営業変更情報です。営業時間や営業影響は公式情報で確認してください。",
          "startsAt": null,
          "endsAt": null,
          "sourceQuote": "headrockcg",
          "extractionConfidence": "0.55",
          "reviewStatus": "pending",
          "decisionNote": "headrockcgの公式Instagramから営業時間・休業変更候補を検出。日付候補は未確定。Adminで変更日、営業時間、休業/短縮営業の範囲を確認してください。根拠抜粋: headrockcg"
        },
        {
          "eventSourceId": "29729a2e-530f-4bd6-a77f-f3d9a586f18e",
          "handle": "headrockcg",
          "displayName": "headrockcg",
          "sourceUrl": "https://www.instagram.com/p/DYUIE7ukYUn/",
          "sourceExternalId": "DYUIE7ukYUn",
          "sourcePostedAt": null,
          "classification": "notice",
          "title": "headrockcg  イベント",
          "summary": "headrockcgの公式情報に基づくイベント情報です。内容や参加条件は公式情報で確認してください。",
          "startsAt": null,
          "endsAt": null,
          "sourceQuote": "headrockcg",
          "extractionConfidence": "0.40",
          "reviewStatus": "ignored",
          "decisionNote": "Browser roller found no calendar-worthy event signal in the visible post text."
        },
        {
          "eventSourceId": "29729a2e-530f-4bd6-a77f-f3d9a586f18e",
          "handle": "headrockcg",
          "displayName": "headrockcg",
          "sourceUrl": "https://www.instagram.com/p/DYUCWdQEXwm/",
          "sourceExternalId": "DYUCWdQEXwm",
          "sourcePostedAt": "2026-05-26T00:00:00.000Z",
          "classification": "notice",
          "title": "headrockcg  イベント",
          "summary": "headrockcgの公式情報に基づくイベント情報です。内容や参加条件は公式情報で確認してください。",
          "startsAt": null,
          "endsAt": null,
          "sourceQuote": "headrockcg",
          "extractionConfidence": "0.40",
          "reviewStatus": "ignored",
          "decisionNote": "Browser roller found no calendar-worthy event signal in the visible post text."
        }
      ],
      "postsSeen": 12,
      "newPostsOpened": 3,
      "duplicatePostsSkipped": 9,
      "lookbackPostsSkipped": 0,
      "inspectionMode": "backfill",
      "lookbackCutoff": "2026-03-21T16:14:49.257Z",
      "noRecentPosts": false,
      "error": null,
      "failureCategory": null,
      "failureDetail": null
    },
    {
      "eventSourceId": "130a0146-a8f8-4f45-bb5d-8f7680b3cc24",
      "handle": "okkurock",
      "displayName": "okkurock",
      "sourceUrl": "https://www.instagram.com/okkurock/",
      "ok": true,
      "deferred": false,
      "posts": [
        {
          "eventSourceId": "130a0146-a8f8-4f45-bb5d-8f7680b3cc24",
          "handle": "okkurock",
          "displayName": "okkurock",
          "sourceUrl": "https://www.instagram.com/p/DYiKBYEk6fI/",
          "sourceExternalId": "DYiKBYEk6fI",
          "sourcePostedAt": null,
          "classification": "notice",
          "title": "okkurock  イベント",
          "summary": "okkurockの公式情報に基づくイベント情報です。内容や参加条件は公式情報で確認してください。",
          "startsAt": null,
          "endsAt": null,
          "sourceQuote": "okkurock",
          "extractionConfidence": "0.40",
          "reviewStatus": "ignored",
          "decisionNote": "Browser roller found no calendar-worthy event signal in the visible post text."
        },
        {
          "eventSourceId": "130a0146-a8f8-4f45-bb5d-8f7680b3cc24",
          "handle": "okkurock",
          "displayName": "okkurock",
          "sourceUrl": "https://www.instagram.com/p/DYgHzu6TleX/",
          "sourceExternalId": "DYgHzu6TleX",
          "sourcePostedAt": null,
          "classification": "notice",
          "title": "okkurock 2026/06/01 イベント",
          "summary": "okkurockの公式情報に基づく2026/06/01のイベント情報です。内容や参加条件は公式情報で確認してください。",
          "startsAt": "2026-06-01T09:00:00.000Z",
          "endsAt": "2026-06-01T10:00:00.000Z",
          "sourceQuote": "okkurock",
          "extractionConfidence": "0.40",
          "reviewStatus": "ignored",
          "decisionNote": "Browser roller found no calendar-worthy event signal in the visible post text."
        },
        {
          "eventSourceId": "130a0146-a8f8-4f45-bb5d-8f7680b3cc24",
          "handle": "okkurock",
          "displayName": "okkurock",
          "sourceUrl": "https://www.instagram.com/p/DYdR-liE8ul/",
          "sourceExternalId": "DYdR-liE8ul",
          "sourcePostedAt": null,
          "classification": "notice",
          "title": "okkurock  イベント",
          "summary": "okkurockの公式情報に基づくイベント情報です。内容や参加条件は公式情報で確認してください。",
          "startsAt": null,
          "endsAt": null,
          "sourceQuote": "okkurock",
          "extractionConfidence": "0.40",
          "reviewStatus": "ignored",
          "decisionNote": "Browser roller found no calendar-worthy event signal in the visible post text."
        }
      ],
      "postsSeen": 12,
      "newPostsOpened": 3,
      "duplicatePostsSkipped": 9,
      "lookbackPostsSkipped": 0,
      "inspectionMode": "backfill",
      "lookbackCutoff": "2026-03-21T16:14:49.257Z",
      "noRecentPosts": false,
      "error": null,
      "failureCategory": null,
      "failureDetail": null
    },
    {
      "eventSourceId": "980b0f60-2f81-4f01-b602-b141409f808e",
      "handle": "penguinclimb",
      "displayName": "penguinclimb",
      "sourceUrl": "https://www.instagram.com/penguinclimb/",
      "ok": true,
      "deferred": false,
      "posts": [
        {
          "eventSourceId": "980b0f60-2f81-4f01-b602-b141409f808e",
          "handle": "penguinclimb",
          "displayName": "penguinclimb",
          "sourceUrl": "https://www.instagram.com/reel/DYjerubKlbo/",
          "sourceExternalId": "DYjerubKlbo",
          "sourcePostedAt": null,
          "classification": "notice",
          "title": "penguinclimb 2026/06/07 イベント",
          "summary": "penguinclimbの公式情報に基づく2026/06/07のイベント情報です。内容や参加条件は公式情報で確認してください。",
          "startsAt": "2026-06-07T01:00:00.000Z",
          "endsAt": "2026-06-07T02:00:00.000Z",
          "sourceQuote": "hiromi_artist",
          "extractionConfidence": "0.40",
          "reviewStatus": "ignored",
          "decisionNote": "Browser roller found no calendar-worthy event signal in the visible post text."
        },
        {
          "eventSourceId": "980b0f60-2f81-4f01-b602-b141409f808e",
          "handle": "penguinclimb",
          "displayName": "penguinclimb",
          "sourceUrl": "https://www.instagram.com/p/DYg_7etErVS/",
          "sourceExternalId": "DYg_7etErVS",
          "sourcePostedAt": "2026-05-24T00:00:00.000Z",
          "classification": "notice",
          "title": "penguinclimb 2026/05/24 イベント",
          "summary": "penguinclimbの公式情報に基づく2026/05/24のイベント情報です。内容や参加条件は公式情報で確認してください。",
          "startsAt": "2026-05-24T01:00:00.000Z",
          "endsAt": "2026-05-24T02:00:00.000Z",
          "sourceQuote": "penguinclimb",
          "extractionConfidence": "0.40",
          "reviewStatus": "ignored",
          "decisionNote": "Browser roller found no calendar-worthy event signal in the visible post text."
        },
        {
          "eventSourceId": "980b0f60-2f81-4f01-b602-b141409f808e",
          "handle": "penguinclimb",
          "displayName": "penguinclimb",
          "sourceUrl": "https://www.instagram.com/reel/DYgtXyyyTfY/",
          "sourceExternalId": "DYgtXyyyTfY",
          "sourcePostedAt": null,
          "classification": "notice",
          "title": "penguinclimb 2026/06/07 イベント",
          "summary": "penguinclimbの公式情報に基づく2026/06/07のイベント情報です。内容や参加条件は公式情報で確認してください。",
          "startsAt": "2026-06-07T01:00:00.000Z",
          "endsAt": "2026-06-07T02:00:00.000Z",
          "sourceQuote": "penguinclimb",
          "extractionConfidence": "0.40",
          "reviewStatus": "ignored",
          "decisionNote": "Browser roller found no calendar-worthy event signal in the visible post text."
        }
      ],
      "postsSeen": 12,
      "newPostsOpened": 3,
      "duplicatePostsSkipped": 9,
      "lookbackPostsSkipped": 0,
      "inspectionMode": "backfill",
      "lookbackCutoff": "2026-03-21T16:14:49.257Z",
      "noRecentPosts": false,
      "error": null,
      "failureCategory": null,
      "failureDetail": null
    },
    {
      "eventSourceId": "1e1c5950-4893-4760-bb9c-d11891dc09e5",
      "handle": "b.g.funny",
      "displayName": "ボルダリングガレージ FUNNY（ファニー）",
      "sourceUrl": "https://www.instagram.com/b.g.funny/",
      "ok": true,
      "deferred": false,
      "posts": [
        {
          "eventSourceId": "1e1c5950-4893-4760-bb9c-d11891dc09e5",
          "handle": "b.g.funny",
          "displayName": "ボルダリングガレージ FUNNY（ファニー）",
          "sourceUrl": "https://www.instagram.com/p/DYeJu8fk6IK/",
          "sourceExternalId": "DYeJu8fk6IK",
          "sourcePostedAt": null,
          "classification": "notice",
          "title": "ボルダリングガレージ FUNNY（ファニー） 2026/05/02 イベント",
          "summary": "ボルダリングガレージ FUNNY（ファニー）の公式情報に基づく2026/05/02のイベント情報です。内容や参加条件は公式情報で確認してください。",
          "startsAt": "2026-05-02T01:00:00.000Z",
          "endsAt": "2026-05-02T12:00:00.000Z",
          "sourceQuote": "b.g.funny",
          "extractionConfidence": "0.40",
          "reviewStatus": "ignored",
          "decisionNote": "Browser roller found no calendar-worthy event signal in the visible post text."
        },
        {
          "eventSourceId": "1e1c5950-4893-4760-bb9c-d11891dc09e5",
          "handle": "b.g.funny",
          "displayName": "ボルダリングガレージ FUNNY（ファニー）",
          "sourceUrl": "https://www.instagram.com/p/DYUnlBzzEBg/",
          "sourceExternalId": "DYUnlBzzEBg",
          "sourcePostedAt": null,
          "classification": "notice",
          "title": "ボルダリングガレージ FUNNY（ファニー）  イベント",
          "summary": "ボルダリングガレージ FUNNY（ファニー）の公式情報に基づくイベント情報です。内容や参加条件は公式情報で確認してください。",
          "startsAt": null,
          "endsAt": null,
          "sourceQuote": "b.g.funny",
          "extractionConfidence": "0.40",
          "reviewStatus": "ignored",
          "decisionNote": "Browser roller found no calendar-worthy event signal in the visible post text."
        },
        {
          "eventSourceId": "1e1c5950-4893-4760-bb9c-d11891dc09e5",
          "handle": "b.g.funny",
          "displayName": "ボルダリングガレージ FUNNY（ファニー）",
          "sourceUrl": "https://www.instagram.com/reel/DYJgckUzaCR/",
          "sourceExternalId": "DYJgckUzaCR",
          "sourcePostedAt": null,
          "classification": "notice",
          "title": "ボルダリングガレージ FUNNY（ファニー） 2026/07/01 イベント",
          "summary": "ボルダリングガレージ FUNNY（ファニー）の公式情報に基づく2026/07/01のイベント情報です。内容や参加条件は公式情報で確認してください。",
          "startsAt": "2026-07-01T01:00:00.000Z",
          "endsAt": "2026-07-01T02:00:00.000Z",
          "sourceQuote": "b.g.funny",
          "extractionConfidence": "0.40",
          "reviewStatus": "ignored",
          "decisionNote": "Browser roller found no calendar-worthy event signal in the visible post text."
        }
      ],
      "postsSeen": 12,
      "newPostsOpened": 3,
      "duplicatePostsSkipped": 9,
      "lookbackPostsSkipped": 0,
      "inspectionMode": "backfill",
      "lookbackCutoff": "2026-03-21T16:14:49.257Z",
      "noRecentPosts": false,
      "error": null,
      "failureCategory": null,
      "failureDetail": null
    },
    {
      "eventSourceId": "230beec0-b638-4d8d-acb9-b0d6c2dd6750",
      "handle": "bouldering_gym_share",
      "displayName": "ボルダリングジム Share（シェア）",
      "sourceUrl": "https://www.instagram.com/bouldering_gym_share/",
      "ok": true,
      "deferred": false,
      "posts": [
        {
          "eventSourceId": "230beec0-b638-4d8d-acb9-b0d6c2dd6750",
          "handle": "bouldering_gym_share",
          "displayName": "ボルダリングジム Share（シェア）",
          "sourceUrl": "https://www.instagram.com/reel/DYjvzD1MVkt/",
          "sourceExternalId": "DYjvzD1MVkt",
          "sourcePostedAt": null,
          "classification": "notice",
          "title": "ボルダリングジム Share（シェア） 2026/07/02 イベント",
          "summary": "ボルダリングジム Share（シェア）の公式情報に基づく2026/07/02のイベント情報です。内容や参加条件は公式情報で確認してください。",
          "startsAt": "2026-07-02T01:00:00.000Z",
          "endsAt": "2026-07-02T02:00:00.000Z",
          "sourceQuote": "bouldering_gym_share",
          "extractionConfidence": "0.40",
          "reviewStatus": "ignored",
          "decisionNote": "Browser roller found no calendar-worthy event signal in the visible post text."
        },
        {
          "eventSourceId": "230beec0-b638-4d8d-acb9-b0d6c2dd6750",
          "handle": "bouldering_gym_share",
          "displayName": "ボルダリングジム Share（シェア）",
          "sourceUrl": "https://www.instagram.com/p/DYeuw6pmXFX/",
          "sourceExternalId": "DYeuw6pmXFX",
          "sourcePostedAt": "2026-05-23T00:00:00.000Z",
          "classification": "event",
          "title": "ボルダリングジム Share（シェア） 2026/05/23 イベント",
          "summary": "ボルダリングジム Share（シェア）の公式情報に基づく2026/05/23のイベント情報です。内容や参加条件は公式情報で確認してください。",
          "startsAt": "2026-05-23T01:00:00.000Z",
          "endsAt": "2026-05-23T02:00:00.000Z",
          "sourceQuote": "bouldering_gym_share",
          "extractionConfidence": "0.72",
          "reviewStatus": "pending",
          "decisionNote": "ボルダリングジム Share（シェア）の公式Instagramからイベント候補を検出。日付候補は2026/05/23。Adminで開催日、内容、参加条件を確認してください。根拠抜粋: bouldering_gym_share"
        },
        {
          "eventSourceId": "230beec0-b638-4d8d-acb9-b0d6c2dd6750",
          "handle": "bouldering_gym_share",
          "displayName": "ボルダリングジム Share（シェア）",
          "sourceUrl": "https://www.instagram.com/reel/DYY-5GwR6HU/",
          "sourceExternalId": "DYY-5GwR6HU",
          "sourcePostedAt": null,
          "classification": "notice",
          "title": "ボルダリングジム Share（シェア） 2026/11/11 イベント",
          "summary": "ボルダリングジム Share（シェア）の公式情報に基づく2026/11/11のイベント情報です。内容や参加条件は公式情報で確認してください。",
          "startsAt": "2026-11-11T01:00:00.000Z",
          "endsAt": "2026-11-11T02:00:00.000Z",
          "sourceQuote": "bouldering_gym_share",
          "extractionConfidence": "0.40",
          "reviewStatus": "ignored",
          "decisionNote": "Browser roller found no calendar-worthy event signal in the visible post text."
        }
      ],
      "postsSeen": 12,
      "newPostsOpened": 3,
      "duplicatePostsSkipped": 9,
      "lookbackPostsSkipped": 0,
      "inspectionMode": "backfill",
      "lookbackCutoff": "2026-03-21T16:14:49.257Z",
      "noRecentPosts": false,
      "error": null,
      "failureCategory": null,
      "failureDetail": null
    },
    {
      "eventSourceId": "1f04c6db-0b8f-4dc0-94a4-9416dfa234fb",
      "handle": "climbing_gym_cozy",
      "displayName": "クライミングジム COZY",
      "sourceUrl": "https://www.instagram.com/climbing_gym_cozy/",
      "ok": true,
      "deferred": false,
      "posts": [
        {
          "eventSourceId": "1f04c6db-0b8f-4dc0-94a4-9416dfa234fb",
          "handle": "climbing_gym_cozy",
          "displayName": "クライミングジム COZY",
          "sourceUrl": "https://www.instagram.com/p/DWnAeWvAaHB/",
          "sourceExternalId": "DWnAeWvAaHB",
          "sourcePostedAt": "2026-04-02T00:00:00.000Z",
          "classification": "notice",
          "title": "クライミングジム COZY 2026/04/05 イベント",
          "summary": "クライミングジム COZYの公式情報に基づく2026/04/05のイベント情報です。内容や参加条件は公式情報で確認してください。",
          "startsAt": "2026-04-05T06:00:00.000Z",
          "endsAt": "2026-04-05T07:00:00.000Z",
          "sourceQuote": "kotoariki_citta",
          "extractionConfidence": "0.40",
          "reviewStatus": "ignored",
          "decisionNote": "Browser roller found no calendar-worthy event signal in the visible post text."
        },
        {
          "eventSourceId": "1f04c6db-0b8f-4dc0-94a4-9416dfa234fb",
          "handle": "climbing_gym_cozy",
          "displayName": "クライミングジム COZY",
          "sourceUrl": "https://www.instagram.com/p/DV8LA99Aa7h/",
          "sourceExternalId": "DV8LA99Aa7h",
          "sourcePostedAt": "2026-03-16T00:00:00.000Z",
          "classification": "recruit",
          "title": "クライミングジム COZY 2026/03/17 イベント",
          "summary": "クライミングジム COZYの公式情報に基づく2026/03/17のイベント情報です。内容や参加条件は公式情報で確認してください。",
          "startsAt": null,
          "endsAt": null,
          "sourceQuote": "climbing_gym_cozy",
          "extractionConfidence": "0.30",
          "reviewStatus": "ignored",
          "decisionNote": "Ignored by Instagram backfill lookback guard: visible posted date is older than 60 days."
        },
        {
          "eventSourceId": "1f04c6db-0b8f-4dc0-94a4-9416dfa234fb",
          "handle": "climbing_gym_cozy",
          "displayName": "クライミングジム COZY",
          "sourceUrl": "https://www.instagram.com/p/DVsBN1pAa1h/",
          "sourceExternalId": "DVsBN1pAa1h",
          "sourcePostedAt": "2026-03-10T00:00:00.000Z",
          "classification": "event",
          "title": "クライミングジム COZY 2026/03/10 イベント",
          "summary": "クライミングジム COZYの公式情報に基づく2026/03/10のイベント情報です。内容や参加条件は公式情報で確認してください。",
          "startsAt": null,
          "endsAt": null,
          "sourceQuote": "climbing_gym_cozy",
          "extractionConfidence": "0.30",
          "reviewStatus": "ignored",
          "decisionNote": "Ignored by Instagram backfill lookback guard: visible posted date is older than 60 days."
        }
      ],
      "postsSeen": 12,
      "newPostsOpened": 3,
      "duplicatePostsSkipped": 9,
      "lookbackPostsSkipped": 2,
      "inspectionMode": "backfill",
      "lookbackCutoff": "2026-03-21T16:14:49.257Z",
      "noRecentPosts": false,
      "error": null,
      "failureCategory": null,
      "failureDetail": null
    },
    {
      "eventSourceId": "15beb98e-1f8b-40b2-badc-791514039786",
      "handle": "climbinggym_hutte",
      "displayName": "クライミングジム Hutte（ヒュッテ）",
      "sourceUrl": "https://www.instagram.com/climbinggym_hutte/",
      "ok": true,
      "deferred": false,
      "posts": [
        {
          "eventSourceId": "15beb98e-1f8b-40b2-badc-791514039786",
          "handle": "climbinggym_hutte",
          "displayName": "クライミングジム Hutte（ヒュッテ）",
          "sourceUrl": "https://www.instagram.com/p/DXrkBtYGfDQ/",
          "sourceExternalId": "DXrkBtYGfDQ",
          "sourcePostedAt": "2026-04-29T00:00:00.000Z",
          "classification": "notice",
          "title": "クライミングジム Hutte（ヒュッテ） 2026/04/29 イベント",
          "summary": "クライミングジム Hutte（ヒュッテ）の公式情報に基づく2026/04/29のイベント情報です。内容や参加条件は公式情報で確認してください。",
          "startsAt": "2026-04-29T01:00:00.000Z",
          "endsAt": "2026-04-29T02:00:00.000Z",
          "sourceQuote": "climbinggym_hutte",
          "extractionConfidence": "0.40",
          "reviewStatus": "ignored",
          "decisionNote": "Browser roller found no calendar-worthy event signal in the visible post text."
        },
        {
          "eventSourceId": "15beb98e-1f8b-40b2-badc-791514039786",
          "handle": "climbinggym_hutte",
          "displayName": "クライミングジム Hutte（ヒュッテ）",
          "sourceUrl": "https://www.instagram.com/p/DXZeVkqAhwB/",
          "sourceExternalId": "DXZeVkqAhwB",
          "sourcePostedAt": "2026-04-22T00:00:00.000Z",
          "classification": "recruit",
          "title": "クライミングジム Hutte（ヒュッテ） 2026/04/22 イベント",
          "summary": "クライミングジム Hutte（ヒュッテ）の公式情報に基づく2026/04/22のイベント情報です。内容や参加条件は公式情報で確認してください。",
          "startsAt": "2026-04-22T01:00:00.000Z",
          "endsAt": "2026-04-22T02:00:00.000Z",
          "sourceQuote": "climbinggym_hutte",
          "extractionConfidence": "0.40",
          "reviewStatus": "ignored",
          "decisionNote": "Recruiting post; tracked to avoid repeated inspection but not a public calendar item."
        },
        {
          "eventSourceId": "15beb98e-1f8b-40b2-badc-791514039786",
          "handle": "climbinggym_hutte",
          "displayName": "クライミングジム Hutte（ヒュッテ）",
          "sourceUrl": "https://www.instagram.com/reel/DXCB9gSArfF/",
          "sourceExternalId": "DXCB9gSArfF",
          "sourcePostedAt": null,
          "classification": "notice",
          "title": "クライミングジム Hutte（ヒュッテ） 2026/07/02 イベント",
          "summary": "クライミングジム Hutte（ヒュッテ）の公式情報に基づく2026/07/02のイベント情報です。内容や参加条件は公式情報で確認してください。",
          "startsAt": "2026-07-02T01:00:00.000Z",
          "endsAt": "2026-07-02T02:00:00.000Z",
          "sourceQuote": "climbinggym_hutte",
          "extractionConfidence": "0.40",
          "reviewStatus": "ignored",
          "decisionNote": "Browser roller found no calendar-worthy event signal in the visible post text."
        }
      ],
      "postsSeen": 24,
      "newPostsOpened": 3,
      "duplicatePostsSkipped": 21,
      "lookbackPostsSkipped": 0,
      "inspectionMode": "backfill",
      "lookbackCutoff": "2026-03-21T16:14:49.257Z",
      "noRecentPosts": false,
      "error": null,
      "failureCategory": null,
      "failureDetail": null
    },
    {
      "eventSourceId": "33933782-2ad8-4000-afae-772c5f05ecce",
      "handle": "climbrise2016",
      "displayName": "クライミングジム RISE（ライズ）",
      "sourceUrl": "https://www.instagram.com/climbrise2016/",
      "ok": true,
      "deferred": false,
      "posts": [
        {
          "eventSourceId": "33933782-2ad8-4000-afae-772c5f05ecce",
          "handle": "climbrise2016",
          "displayName": "クライミングジム RISE（ライズ）",
          "sourceUrl": "https://www.instagram.com/p/DYBVMz4E9Qh/",
          "sourceExternalId": "DYBVMz4E9Qh",
          "sourcePostedAt": "2026-05-07T00:00:00.000Z",
          "classification": "notice",
          "title": "クライミングジム RISE（ライズ）  イベント",
          "summary": "クライミングジム RISE（ライズ）の公式情報に基づくイベント情報です。内容や参加条件は公式情報で確認してください。",
          "startsAt": null,
          "endsAt": null,
          "sourceQuote": "climbrise2016",
          "extractionConfidence": "0.40",
          "reviewStatus": "ignored",
          "decisionNote": "Browser roller found no calendar-worthy event signal in the visible post text."
        },
        {
          "eventSourceId": "33933782-2ad8-4000-afae-772c5f05ecce",
          "handle": "climbrise2016",
          "displayName": "クライミングジム RISE（ライズ）",
          "sourceUrl": "https://www.instagram.com/p/DXvxU0kE8qM/",
          "sourceExternalId": "DXvxU0kE8qM",
          "sourcePostedAt": "2026-04-30T00:00:00.000Z",
          "classification": "private_booking",
          "title": "クライミングジム RISE（ライズ） 2026/05/19 貸切",
          "summary": "クライミングジム RISE（ライズ）の公式情報に基づく2026/05/19の貸切・利用制限情報です。一般利用への影響は公式情報で確認してください。",
          "startsAt": "2026-05-19T01:00:00.000Z",
          "endsAt": "2026-05-21T12:00:00.000Z",
          "sourceQuote": "climbrise2016",
          "extractionConfidence": "0.72",
          "reviewStatus": "pending",
          "decisionNote": "クライミングジム RISE（ライズ）の公式Instagramから貸切・利用制限候補を検出。日付候補は2026/05/19。Adminで貸切日時、一般利用への影響を確認してください。根拠抜粋: climbrise2016"
        },
        {
          "eventSourceId": "33933782-2ad8-4000-afae-772c5f05ecce",
          "handle": "climbrise2016",
          "displayName": "クライミングジム RISE（ライズ）",
          "sourceUrl": "https://www.instagram.com/p/DXszKmOk9VN/",
          "sourceExternalId": "DXszKmOk9VN",
          "sourcePostedAt": "2026-04-29T00:00:00.000Z",
          "classification": "notice",
          "title": "クライミングジム RISE（ライズ）  イベント",
          "summary": "クライミングジム RISE（ライズ）の公式情報に基づくイベント情報です。内容や参加条件は公式情報で確認してください。",
          "startsAt": null,
          "endsAt": null,
          "sourceQuote": "climbrise2016",
          "extractionConfidence": "0.40",
          "reviewStatus": "ignored",
          "decisionNote": "Browser roller found no calendar-worthy event signal in the visible post text."
        }
      ],
      "postsSeen": 12,
      "newPostsOpened": 3,
      "duplicatePostsSkipped": 9,
      "lookbackPostsSkipped": 0,
      "inspectionMode": "backfill",
      "lookbackCutoff": "2026-03-21T16:14:49.257Z",
      "noRecentPosts": false,
      "error": null,
      "failureCategory": null,
      "failureDetail": null
    },
    {
      "eventSourceId": "86e485c9-55ea-48ea-b4bc-be876064ff75",
      "handle": "quartier_de_roche",
      "displayName": "クライミングパーク カルチェロッシュ",
      "sourceUrl": "https://www.instagram.com/quartier_de_roche/",
      "ok": true,
      "deferred": false,
      "posts": [
        {
          "eventSourceId": "86e485c9-55ea-48ea-b4bc-be876064ff75",
          "handle": "quartier_de_roche",
          "displayName": "クライミングパーク カルチェロッシュ",
          "sourceUrl": "https://www.instagram.com/reel/DX39-3xSgiU/",
          "sourceExternalId": "DX39-3xSgiU",
          "sourcePostedAt": null,
          "classification": "notice",
          "title": "クライミングパーク カルチェロッシュ  イベント",
          "summary": "クライミングパーク カルチェロッシュの公式情報に基づくイベント情報です。内容や参加条件は公式情報で確認してください。",
          "startsAt": null,
          "endsAt": null,
          "sourceQuote": "quartier_de_roche",
          "extractionConfidence": "0.40",
          "reviewStatus": "ignored",
          "decisionNote": "Browser roller found no calendar-worthy event signal in the visible post text."
        },
        {
          "eventSourceId": "86e485c9-55ea-48ea-b4bc-be876064ff75",
          "handle": "quartier_de_roche",
          "displayName": "クライミングパーク カルチェロッシュ",
          "sourceUrl": "https://www.instagram.com/reel/DX1kQaxSSkr/",
          "sourceExternalId": "DX1kQaxSSkr",
          "sourcePostedAt": null,
          "classification": "notice",
          "title": "クライミングパーク カルチェロッシュ  イベント",
          "summary": "クライミングパーク カルチェロッシュの公式情報に基づくイベント情報です。内容や参加条件は公式情報で確認してください。",
          "startsAt": null,
          "endsAt": null,
          "sourceQuote": "quartier_de_roche",
          "extractionConfidence": "0.40",
          "reviewStatus": "ignored",
          "decisionNote": "Browser roller found no calendar-worthy event signal in the visible post text."
        },
        {
          "eventSourceId": "86e485c9-55ea-48ea-b4bc-be876064ff75",
          "handle": "quartier_de_roche",
          "displayName": "クライミングパーク カルチェロッシュ",
          "sourceUrl": "https://www.instagram.com/p/DX1AFxnklIv/",
          "sourceExternalId": "DX1AFxnklIv",
          "sourcePostedAt": "2026-05-02T00:00:00.000Z",
          "classification": "notice",
          "title": "クライミングパーク カルチェロッシュ 2026/05/02 イベント",
          "summary": "クライミングパーク カルチェロッシュの公式情報に基づく2026/05/02のイベント情報です。内容や参加条件は公式情報で確認してください。",
          "startsAt": "2026-05-02T01:00:00.000Z",
          "endsAt": "2026-05-02T02:00:00.000Z",
          "sourceQuote": "quartier_de_roche",
          "extractionConfidence": "0.40",
          "reviewStatus": "ignored",
          "decisionNote": "Browser roller found no calendar-worthy event signal in the visible post text."
        }
      ],
      "postsSeen": 12,
      "newPostsOpened": 3,
      "duplicatePostsSkipped": 9,
      "lookbackPostsSkipped": 0,
      "inspectionMode": "backfill",
      "lookbackCutoff": "2026-03-21T16:14:49.257Z",
      "noRecentPosts": false,
      "error": null,
      "failureCategory": null,
      "failureDetail": null
    },
    {
      "eventSourceId": "02d44afc-a542-4d6e-8e36-042215e7a55e",
      "handle": "rhinoandbird_nishinippori",
      "displayName": "Rhino and Bird（ライノアンドバード）",
      "sourceUrl": "https://www.instagram.com/rhinoandbird_nishinippori/",
      "ok": true,
      "deferred": false,
      "posts": [
        {
          "eventSourceId": "02d44afc-a542-4d6e-8e36-042215e7a55e",
          "handle": "rhinoandbird_nishinippori",
          "displayName": "Rhino and Bird（ライノアンドバード）",
          "sourceUrl": "https://www.instagram.com/p/DYToK7_x9k6/",
          "sourceExternalId": "DYToK7_x9k6",
          "sourcePostedAt": null,
          "classification": "route_set",
          "title": "Rhino and Bird（ライノアンドバード） 2026/05/25 セット",
          "summary": "Rhino and Bird（ライノアンドバード）の公式情報に基づく2026/05/25のセット・ホールド替え情報です。対象エリアや利用制限は公式情報で確認してください。",
          "startsAt": "2026-05-25T01:00:00.000Z",
          "endsAt": "2026-05-26T12:00:00.000Z",
          "sourceQuote": "rhinoandbird_nishinippori",
          "extractionConfidence": "0.72",
          "reviewStatus": "pending",
          "decisionNote": "Rhino and Bird（ライノアンドバード）の公式Instagramからセット・ホールド替え候補を検出。日付候補は2026/05/25。Adminで対象エリア、作業期間、利用制限を確認してください。根拠抜粋: rhinoandbird_nishinippori"
        },
        {
          "eventSourceId": "02d44afc-a542-4d6e-8e36-042215e7a55e",
          "handle": "rhinoandbird_nishinippori",
          "displayName": "Rhino and Bird（ライノアンドバード）",
          "sourceUrl": "https://www.instagram.com/p/DVcyTgDkdIN/",
          "sourceExternalId": "DVcyTgDkdIN",
          "sourcePostedAt": "2026-03-04T00:00:00.000Z",
          "classification": "notice",
          "title": "Rhino and Bird（ライノアンドバード） 2026/03/24 イベント",
          "summary": "Rhino and Bird（ライノアンドバード）の公式情報に基づく2026/03/24のイベント情報です。内容や参加条件は公式情報で確認してください。",
          "startsAt": null,
          "endsAt": null,
          "sourceQuote": "rhinoandbird_nishinippori",
          "extractionConfidence": "0.30",
          "reviewStatus": "ignored",
          "decisionNote": "Ignored by Instagram backfill lookback guard: visible posted date is older than 60 days."
        },
        {
          "eventSourceId": "02d44afc-a542-4d6e-8e36-042215e7a55e",
          "handle": "rhinoandbird_nishinippori",
          "displayName": "Rhino and Bird（ライノアンドバード）",
          "sourceUrl": "https://www.instagram.com/p/DU7VRzRkVvb/",
          "sourceExternalId": "DU7VRzRkVvb",
          "sourcePostedAt": "2026-02-19T00:00:00.000Z",
          "classification": "route_set",
          "title": "Rhino and Bird（ライノアンドバード） 2026/03/02 セット",
          "summary": "Rhino and Bird（ライノアンドバード）の公式情報に基づく2026/03/02のセット・ホールド替え情報です。対象エリアや利用制限は公式情報で確認してください。",
          "startsAt": null,
          "endsAt": null,
          "sourceQuote": "rhinoandbird_nishinippori",
          "extractionConfidence": "0.30",
          "reviewStatus": "ignored",
          "decisionNote": "Ignored by Instagram backfill lookback guard: visible posted date is older than 60 days."
        }
      ],
      "postsSeen": 12,
      "newPostsOpened": 3,
      "duplicatePostsSkipped": 9,
      "lookbackPostsSkipped": 2,
      "inspectionMode": "backfill",
      "lookbackCutoff": "2026-03-21T16:14:49.257Z",
      "noRecentPosts": false,
      "error": null,
      "failureCategory": null,
      "failureDetail": null
    },
    {
      "eventSourceId": "8e81426f-f0ee-45a1-ac86-6625148f8e1d",
      "handle": "rockbeans.insta",
      "displayName": "クライミングジム ROCKBEANS（ロックビーンズ）",
      "sourceUrl": "https://www.instagram.com/rockbeans.insta/",
      "ok": true,
      "deferred": false,
      "posts": [
        {
          "eventSourceId": "8e81426f-f0ee-45a1-ac86-6625148f8e1d",
          "handle": "rockbeans.insta",
          "displayName": "クライミングジム ROCKBEANS（ロックビーンズ）",
          "sourceUrl": "https://www.instagram.com/p/DGXSo45yR9j/",
          "sourceExternalId": "DGXSo45yR9j",
          "sourcePostedAt": "2025-02-22T00:00:00.000Z",
          "classification": "recruit",
          "title": "クライミングジム ROCKBEANS（ロックビーンズ） 2025/02/22 イベント",
          "summary": "クライミングジム ROCKBEANS（ロックビーンズ）の公式情報に基づく2025/02/22のイベント情報です。内容や参加条件は公式情報で確認してください。",
          "startsAt": null,
          "endsAt": null,
          "sourceQuote": "rockbeans.insta",
          "extractionConfidence": "0.30",
          "reviewStatus": "ignored",
          "decisionNote": "Ignored by Instagram backfill lookback guard: visible posted date is older than 60 days."
        },
        {
          "eventSourceId": "8e81426f-f0ee-45a1-ac86-6625148f8e1d",
          "handle": "rockbeans.insta",
          "displayName": "クライミングジム ROCKBEANS（ロックビーンズ）",
          "sourceUrl": "https://www.instagram.com/p/DGUcHs7SgQQ/",
          "sourceExternalId": "DGUcHs7SgQQ",
          "sourcePostedAt": "2025-02-21T00:00:00.000Z",
          "classification": "notice",
          "title": "クライミングジム ROCKBEANS（ロックビーンズ） 2025/02/21 イベント",
          "summary": "クライミングジム ROCKBEANS（ロックビーンズ）の公式情報に基づく2025/02/21のイベント情報です。内容や参加条件は公式情報で確認してください。",
          "startsAt": null,
          "endsAt": null,
          "sourceQuote": "rockbeans.insta",
          "extractionConfidence": "0.30",
          "reviewStatus": "ignored",
          "decisionNote": "Ignored by Instagram backfill lookback guard: visible posted date is older than 60 days."
        },
        {
          "eventSourceId": "8e81426f-f0ee-45a1-ac86-6625148f8e1d",
          "handle": "rockbeans.insta",
          "displayName": "クライミングジム ROCKBEANS（ロックビーンズ）",
          "sourceUrl": "https://www.instagram.com/p/C-UOj8_SR0H/",
          "sourceExternalId": "C-UOj8_SR0H",
          "sourcePostedAt": "2024-08-06T00:00:00.000Z",
          "classification": "recruit",
          "title": "クライミングジム ROCKBEANS（ロックビーンズ） 2024/08/06 イベント",
          "summary": "クライミングジム ROCKBEANS（ロックビーンズ）の公式情報に基づく2024/08/06のイベント情報です。内容や参加条件は公式情報で確認してください。",
          "startsAt": null,
          "endsAt": null,
          "sourceQuote": "rockbeans.insta",
          "extractionConfidence": "0.30",
          "reviewStatus": "ignored",
          "decisionNote": "Ignored by Instagram backfill lookback guard: visible posted date is older than 60 days."
        }
      ],
      "postsSeen": 12,
      "newPostsOpened": 3,
      "duplicatePostsSkipped": 9,
      "lookbackPostsSkipped": 3,
      "inspectionMode": "backfill",
      "lookbackCutoff": "2026-03-21T16:14:49.257Z",
      "noRecentPosts": false,
      "error": null,
      "failureCategory": null,
      "failureDetail": null
    },
    {
      "eventSourceId": "f5d7c62a-37fb-4253-ab25-f7135be773db",
      "handle": "sloth.gym",
      "displayName": "クライミングジム SLOTH（スロース）",
      "sourceUrl": "https://www.instagram.com/sloth.gym/",
      "ok": true,
      "deferred": false,
      "posts": [
        {
          "eventSourceId": "f5d7c62a-37fb-4253-ab25-f7135be773db",
          "handle": "sloth.gym",
          "displayName": "クライミングジム SLOTH（スロース）",
          "sourceUrl": "https://www.instagram.com/p/DWsUpf-AeY1/",
          "sourceExternalId": "DWsUpf-AeY1",
          "sourcePostedAt": "2026-04-04T00:00:00.000Z",
          "classification": "notice",
          "title": "クライミングジム SLOTH（スロース） 2026/04/04 イベント",
          "summary": "クライミングジム SLOTH（スロース）の公式情報に基づく2026/04/04のイベント情報です。内容や参加条件は公式情報で確認してください。",
          "startsAt": "2026-04-04T01:00:00.000Z",
          "endsAt": "2026-04-04T02:00:00.000Z",
          "sourceQuote": "sloth.gym",
          "extractionConfidence": "0.40",
          "reviewStatus": "ignored",
          "decisionNote": "Browser roller found no calendar-worthy event signal in the visible post text."
        },
        {
          "eventSourceId": "f5d7c62a-37fb-4253-ab25-f7135be773db",
          "handle": "sloth.gym",
          "displayName": "クライミングジム SLOTH（スロース）",
          "sourceUrl": "https://www.instagram.com/p/DWkj_SWAdLk/",
          "sourceExternalId": "DWkj_SWAdLk",
          "sourcePostedAt": "2026-04-01T00:00:00.000Z",
          "classification": "notice",
          "title": "クライミングジム SLOTH（スロース）  イベント",
          "summary": "クライミングジム SLOTH（スロース）の公式情報に基づくイベント情報です。内容や参加条件は公式情報で確認してください。",
          "startsAt": null,
          "endsAt": null,
          "sourceQuote": "sloth.gym",
          "extractionConfidence": "0.40",
          "reviewStatus": "ignored",
          "decisionNote": "Browser roller found no calendar-worthy event signal in the visible post text."
        },
        {
          "eventSourceId": "f5d7c62a-37fb-4253-ab25-f7135be773db",
          "handle": "sloth.gym",
          "displayName": "クライミングジム SLOTH（スロース）",
          "sourceUrl": "https://www.instagram.com/p/DVN8piWAcaN/",
          "sourceExternalId": "DVN8piWAcaN",
          "sourcePostedAt": "2026-02-26T00:00:00.000Z",
          "classification": "notice",
          "title": "クライミングジム SLOTH（スロース） 2026/02/26 イベント",
          "summary": "クライミングジム SLOTH（スロース）の公式情報に基づく2026/02/26のイベント情報です。内容や参加条件は公式情報で確認してください。",
          "startsAt": null,
          "endsAt": null,
          "sourceQuote": "sloth.gym",
          "extractionConfidence": "0.30",
          "reviewStatus": "ignored",
          "decisionNote": "Ignored by Instagram backfill lookback guard: visible posted date is older than 60 days."
        }
      ],
      "postsSeen": 12,
      "newPostsOpened": 3,
      "duplicatePostsSkipped": 9,
      "lookbackPostsSkipped": 1,
      "inspectionMode": "backfill",
      "lookbackCutoff": "2026-03-21T16:14:49.257Z",
      "noRecentPosts": false,
      "error": null,
      "failureCategory": null,
      "failureDetail": null
    },
    {
      "eventSourceId": "d138f4f5-4298-42bc-8905-703e7dde222a",
      "handle": "dbouldering_tsunashima",
      "displayName": "ディーボルダリング 綱島",
      "sourceUrl": "https://www.instagram.com/dbouldering_tsunashima/",
      "ok": true,
      "deferred": false,
      "posts": [
        {
          "eventSourceId": "d138f4f5-4298-42bc-8905-703e7dde222a",
          "handle": "dbouldering_tsunashima",
          "displayName": "ディーボルダリング 綱島",
          "sourceUrl": "https://www.instagram.com/reel/DYgXsC2zDae/",
          "sourceExternalId": "DYgXsC2zDae",
          "sourcePostedAt": null,
          "classification": "notice",
          "title": "ディーボルダリング 綱島  イベント",
          "summary": "ディーボルダリング 綱島の公式情報に基づくイベント情報です。内容や参加条件は公式情報で確認してください。",
          "startsAt": null,
          "endsAt": null,
          "sourceQuote": "dbouldering_tsunashima",
          "extractionConfidence": "0.40",
          "reviewStatus": "ignored",
          "decisionNote": "Browser roller found no calendar-worthy event signal in the visible post text."
        },
        {
          "eventSourceId": "d138f4f5-4298-42bc-8905-703e7dde222a",
          "handle": "dbouldering_tsunashima",
          "displayName": "ディーボルダリング 綱島",
          "sourceUrl": "https://www.instagram.com/p/DYTouMRE0zk/",
          "sourceExternalId": "DYTouMRE0zk",
          "sourcePostedAt": null,
          "classification": "notice",
          "title": "ディーボルダリング 綱島  イベント",
          "summary": "ディーボルダリング 綱島の公式情報に基づくイベント情報です。内容や参加条件は公式情報で確認してください。",
          "startsAt": null,
          "endsAt": null,
          "sourceQuote": "dbouldering_tsunashima",
          "extractionConfidence": "0.40",
          "reviewStatus": "ignored",
          "decisionNote": "Browser roller found no calendar-worthy event signal in the visible post text."
        },
        {
          "eventSourceId": "d138f4f5-4298-42bc-8905-703e7dde222a",
          "handle": "dbouldering_tsunashima",
          "displayName": "ディーボルダリング 綱島",
          "sourceUrl": "https://www.instagram.com/reel/DYMINn2TaS0/",
          "sourceExternalId": "DYMINn2TaS0",
          "sourcePostedAt": null,
          "classification": "notice",
          "title": "ディーボルダリング 綱島 2026/04/05 イベント",
          "summary": "ディーボルダリング 綱島の公式情報に基づく2026/04/05のイベント情報です。内容や参加条件は公式情報で確認してください。",
          "startsAt": "2026-04-05T01:00:00.000Z",
          "endsAt": "2026-04-05T02:00:00.000Z",
          "sourceQuote": "dbouldering_tsunashima",
          "extractionConfidence": "0.40",
          "reviewStatus": "ignored",
          "decisionNote": "Browser roller found no calendar-worthy event signal in the visible post text."
        }
      ],
      "postsSeen": 12,
      "newPostsOpened": 3,
      "duplicatePostsSkipped": 9,
      "lookbackPostsSkipped": 0,
      "inspectionMode": "backfill",
      "lookbackCutoff": "2026-03-21T16:14:49.257Z",
      "noRecentPosts": false,
      "error": null,
      "failureCategory": null,
      "failureDetail": null
    },
    {
      "eventSourceId": "c4471313-b931-43cc-9608-c32a49fbbf96",
      "handle": "granny_bouldering",
      "displayName": "ボルダリングジム GRANNY（グラニー） 南流山店",
      "sourceUrl": "https://www.instagram.com/granny_bouldering/",
      "ok": true,
      "deferred": false,
      "posts": [
        {
          "eventSourceId": "c4471313-b931-43cc-9608-c32a49fbbf96",
          "handle": "granny_bouldering",
          "displayName": "ボルダリングジム GRANNY（グラニー） 南流山店",
          "sourceUrl": "https://www.instagram.com/reel/DYZmhRAB1kB/",
          "sourceExternalId": "DYZmhRAB1kB",
          "sourcePostedAt": null,
          "classification": "notice",
          "title": "ボルダリングジム GRANNY（グラニー） 南流山店  イベント",
          "summary": "ボルダリングジム GRANNY（グラニー） 南流山店の公式情報に基づくイベント情報です。内容や参加条件は公式情報で確認してください。",
          "startsAt": null,
          "endsAt": null,
          "sourceQuote": "granny_bouldering",
          "extractionConfidence": "0.40",
          "reviewStatus": "ignored",
          "decisionNote": "Browser roller found no calendar-worthy event signal in the visible post text."
        },
        {
          "eventSourceId": "c4471313-b931-43cc-9608-c32a49fbbf96",
          "handle": "granny_bouldering",
          "displayName": "ボルダリングジム GRANNY（グラニー） 南流山店",
          "sourceUrl": "https://www.instagram.com/reel/DYZMsu4TKt-/",
          "sourceExternalId": "DYZMsu4TKt-",
          "sourcePostedAt": null,
          "classification": "notice",
          "title": "ボルダリングジム GRANNY（グラニー） 南流山店 2026/07/08 イベント",
          "summary": "ボルダリングジム GRANNY（グラニー） 南流山店の公式情報に基づく2026/07/08のイベント情報です。内容や参加条件は公式情報で確認してください。",
          "startsAt": "2026-07-08T01:00:00.000Z",
          "endsAt": "2026-07-08T02:00:00.000Z",
          "sourceQuote": "granny_bouldering",
          "extractionConfidence": "0.40",
          "reviewStatus": "ignored",
          "decisionNote": "Browser roller found no calendar-worthy event signal in the visible post text."
        },
        {
          "eventSourceId": "c4471313-b931-43cc-9608-c32a49fbbf96",
          "handle": "granny_bouldering",
          "displayName": "ボルダリングジム GRANNY（グラニー） 南流山店",
          "sourceUrl": "https://www.instagram.com/reel/DYWn-dHT69G/",
          "sourceExternalId": "DYWn-dHT69G",
          "sourcePostedAt": null,
          "classification": "notice",
          "title": "ボルダリングジム GRANNY（グラニー） 南流山店 2026/01/02 イベント",
          "summary": "ボルダリングジム GRANNY（グラニー） 南流山店の公式情報に基づく2026/01/02のイベント情報です。内容や参加条件は公式情報で確認してください。",
          "startsAt": "2026-01-02T01:00:00.000Z",
          "endsAt": "2026-01-02T02:00:00.000Z",
          "sourceQuote": "granny_bouldering",
          "extractionConfidence": "0.40",
          "reviewStatus": "ignored",
          "decisionNote": "Browser roller found no calendar-worthy event signal in the visible post text."
        }
      ],
      "postsSeen": 12,
      "newPostsOpened": 3,
      "duplicatePostsSkipped": 9,
      "lookbackPostsSkipped": 0,
      "inspectionMode": "backfill",
      "lookbackCutoff": "2026-03-21T16:14:49.257Z",
      "noRecentPosts": false,
      "error": null,
      "failureCategory": null,
      "failureDetail": null
    },
    {
      "eventSourceId": "806b9f74-2b0b-418f-89df-a1b0ffe51a91",
      "handle": "echoesclimbing",
      "displayName": "ECHOES CLIMBING（エコーズ クライミング）",
      "sourceUrl": "https://www.instagram.com/echoesclimbing/",
      "ok": true,
      "deferred": false,
      "posts": [
        {
          "eventSourceId": "806b9f74-2b0b-418f-89df-a1b0ffe51a91",
          "handle": "echoesclimbing",
          "displayName": "ECHOES CLIMBING（エコーズ クライミング）",
          "sourceUrl": "https://www.instagram.com/reel/DYcPCtlRJhl/",
          "sourceExternalId": "DYcPCtlRJhl",
          "sourcePostedAt": null,
          "classification": "notice",
          "title": "ECHOES CLIMBING（エコーズ クライミング） 2026/12/08 イベント",
          "summary": "ECHOES CLIMBING（エコーズ クライミング）の公式情報に基づく2026/12/08のイベント情報です。内容や参加条件は公式情報で確認してください。",
          "startsAt": "2026-12-08T01:00:00.000Z",
          "endsAt": "2026-12-08T02:00:00.000Z",
          "sourceQuote": "echoesclimbing",
          "extractionConfidence": "0.40",
          "reviewStatus": "ignored",
          "decisionNote": "Browser roller found no calendar-worthy event signal in the visible post text."
        },
        {
          "eventSourceId": "806b9f74-2b0b-418f-89df-a1b0ffe51a91",
          "handle": "echoesclimbing",
          "displayName": "ECHOES CLIMBING（エコーズ クライミング）",
          "sourceUrl": "https://www.instagram.com/reel/DYUOVQORUlN/",
          "sourceExternalId": "DYUOVQORUlN",
          "sourcePostedAt": null,
          "classification": "notice",
          "title": "ECHOES CLIMBING（エコーズ クライミング） 2026/02/07 イベント",
          "summary": "ECHOES CLIMBING（エコーズ クライミング）の公式情報に基づく2026/02/07のイベント情報です。内容や参加条件は公式情報で確認してください。",
          "startsAt": "2026-02-07T01:00:00.000Z",
          "endsAt": "2026-02-07T02:00:00.000Z",
          "sourceQuote": "echoesclimbing",
          "extractionConfidence": "0.40",
          "reviewStatus": "ignored",
          "decisionNote": "Browser roller found no calendar-worthy event signal in the visible post text."
        },
        {
          "eventSourceId": "806b9f74-2b0b-418f-89df-a1b0ffe51a91",
          "handle": "echoesclimbing",
          "displayName": "ECHOES CLIMBING（エコーズ クライミング）",
          "sourceUrl": "https://www.instagram.com/reel/DYRn498xOIx/",
          "sourceExternalId": "DYRn498xOIx",
          "sourcePostedAt": null,
          "classification": "notice",
          "title": "ECHOES CLIMBING（エコーズ クライミング） 2026/03/02 イベント",
          "summary": "ECHOES CLIMBING（エコーズ クライミング）の公式情報に基づく2026/03/02のイベント情報です。内容や参加条件は公式情報で確認してください。",
          "startsAt": "2026-03-02T01:00:00.000Z",
          "endsAt": "2026-03-02T02:00:00.000Z",
          "sourceQuote": "echoesclimbing",
          "extractionConfidence": "0.40",
          "reviewStatus": "ignored",
          "decisionNote": "Browser roller found no calendar-worthy event signal in the visible post text."
        }
      ],
      "postsSeen": 12,
      "newPostsOpened": 3,
      "duplicatePostsSkipped": 9,
      "lookbackPostsSkipped": 0,
      "inspectionMode": "backfill",
      "lookbackCutoff": "2026-03-21T16:14:49.257Z",
      "noRecentPosts": false,
      "error": null,
      "failureCategory": null,
      "failureDetail": null
    },
    {
      "eventSourceId": "78a8cba8-4553-4856-8ec3-fd587d39fb78",
      "handle": "folk_boulderinggym",
      "displayName": "folk（フォーク） ボルダリングジム",
      "sourceUrl": "https://www.instagram.com/folk_boulderinggym/",
      "ok": true,
      "deferred": false,
      "posts": [
        {
          "eventSourceId": "78a8cba8-4553-4856-8ec3-fd587d39fb78",
          "handle": "folk_boulderinggym",
          "displayName": "folk（フォーク） ボルダリングジム",
          "sourceUrl": "https://www.instagram.com/p/DVj5ZdBE8Ej/",
          "sourceExternalId": "DVj5ZdBE8Ej",
          "sourcePostedAt": "2026-03-07T00:00:00.000Z",
          "classification": "notice",
          "title": "folk（フォーク） ボルダリングジム  イベント",
          "summary": "folk（フォーク） ボルダリングジムの公式情報に基づくイベント情報です。内容や参加条件は公式情報で確認してください。",
          "startsAt": null,
          "endsAt": null,
          "sourceQuote": "folk_boulderinggym",
          "extractionConfidence": "0.30",
          "reviewStatus": "ignored",
          "decisionNote": "Ignored by Instagram backfill lookback guard: visible posted date is older than 60 days."
        },
        {
          "eventSourceId": "78a8cba8-4553-4856-8ec3-fd587d39fb78",
          "handle": "folk_boulderinggym",
          "displayName": "folk（フォーク） ボルダリングジム",
          "sourceUrl": "https://www.instagram.com/p/DVhuAw7CSN3/",
          "sourceExternalId": "DVhuAw7CSN3",
          "sourcePostedAt": "2026-03-06T00:00:00.000Z",
          "classification": "private_booking",
          "title": "folk（フォーク） ボルダリングジム 2026/03/07 貸切",
          "summary": "folk（フォーク） ボルダリングジムの公式情報に基づく2026/03/07の貸切・利用制限情報です。一般利用への影響は公式情報で確認してください。",
          "startsAt": null,
          "endsAt": null,
          "sourceQuote": "folk_boulderinggym",
          "extractionConfidence": "0.30",
          "reviewStatus": "ignored",
          "decisionNote": "Ignored by Instagram backfill lookback guard: visible posted date is older than 60 days."
        },
        {
          "eventSourceId": "78a8cba8-4553-4856-8ec3-fd587d39fb78",
          "handle": "folk_boulderinggym",
          "displayName": "folk（フォーク） ボルダリングジム",
          "sourceUrl": "https://www.instagram.com/p/DUX1INZCTvE/",
          "sourceExternalId": "DUX1INZCTvE",
          "sourcePostedAt": "2026-02-05T00:00:00.000Z",
          "classification": "route_set",
          "title": "folk（フォーク） ボルダリングジム 2026/03/04 セット",
          "summary": "folk（フォーク） ボルダリングジムの公式情報に基づく2026/03/04のセット・ホールド替え情報です。対象エリアや利用制限は公式情報で確認してください。",
          "startsAt": null,
          "endsAt": null,
          "sourceQuote": "folk_boulderinggym",
          "extractionConfidence": "0.30",
          "reviewStatus": "ignored",
          "decisionNote": "Ignored by Instagram backfill lookback guard: visible posted date is older than 60 days."
        }
      ],
      "postsSeen": 24,
      "newPostsOpened": 3,
      "duplicatePostsSkipped": 21,
      "lookbackPostsSkipped": 3,
      "inspectionMode": "backfill",
      "lookbackCutoff": "2026-03-21T16:14:49.257Z",
      "noRecentPosts": false,
      "error": null,
      "failureCategory": null,
      "failureDetail": null
    }
  ]
}
