{
  "generatedAt": "2026-05-20T16:20:59.490Z",
  "policy": {
    "savedFields": "page URL, derived source fragment, classification, short summary, short quote, review status",
    "excludedFields": "full page text, copied images, copied videos, HTML snapshots"
  },
  "summary": {
    "sourcesQueued": 7,
    "sourcesFetched": 5,
    "sourcesFailed": 2,
    "observedItems": 10,
    "pendingItems": 10,
    "ignoredItems": 0,
    "calendarCandidates": 10
  },
  "inspections": [
    {
      "handle": "piglet-climbing-gym",
      "displayName": "PIGLET CLIMBING GYM公式サイト",
      "sourceUrl": "https://piglet-climb.com/",
      "sourceType": "official_site",
      "ok": false,
      "error": "site_fetch_failed",
      "failureCategory": "network",
      "failureDetail": "fetch failed",
      "candidates": []
    },
    {
      "handle": "kachill",
      "displayName": "KaChill 公式サイト",
      "sourceUrl": "https://kachill.jimdosite.com/",
      "sourceType": "official_site",
      "ok": false,
      "error": "site_fetch_failed",
      "failureCategory": "access_restricted",
      "failureDetail": "HTTP 403",
      "candidates": []
    },
    {
      "handle": "headrock-climbing",
      "displayName": "HEADROCK CLIMBING GYM 公式サイト",
      "sourceUrl": "https://headrock-climbing.com/",
      "sourceType": "official_site",
      "ok": true,
      "error": null,
      "failureCategory": null,
      "failureDetail": null,
      "candidates": [
        {
          "handle": "headrock-climbing",
          "sourceUrl": "https://headrock-climbing.com/#zac-2026-05-19-event-1",
          "sourceExternalId": "official-site:headrock-climbing:2026-05-19:event:1",
          "classification": "event",
          "title": "HEADROCK CLIMBING GYM 3月末まで延長",
          "summary": "HEADROCK CLIMBING GYMの公式情報に基づく2026/05/19のイベント情報です。内容や参加条件は公式情報で確認してください。",
          "startsAt": "2026-05-19T01:00:00.000Z",
          "endsAt": "2026-05-19T02:00:00.000Z",
          "sourceQuote": "開閉する 施設について 初めての方へ 料金表 スクール クーポン アクセス ONLINE SHOP お問い合わせ 03-6659-5843 NEWS MORE 2026/5/19 キッズクラス体験会開催！ 2026/5/1 2026年5月…",
          "extractionConfidence": "0.60",
          "reviewStatus": "pending",
          "decisionNote": "HEADROCK CLIMBING GYM 公式サイトからイベント候補を検出。日付候補は2026/05/19。Adminで開催日、内容、参加条件を確認してください。根拠抜粋: 開閉する 施設について 初めての方へ 料金表 スクール クーポン アクセス ONLINE SHOP お問い合わせ 03-6659-5843 NEWS MORE 2026/5/19 キッズクラス体験会開催！ 2026/5/1 2026年5月…"
        },
        {
          "handle": "headrock-climbing",
          "sourceUrl": "https://headrock-climbing.com/#zac-2026-05-01-event-2",
          "sourceExternalId": "official-site:headrock-climbing:2026-05-01:event:2",
          "classification": "event",
          "title": "HEADROCK CLIMBING GYM 3月末まで延長",
          "summary": "HEADROCK CLIMBING GYMの公式情報に基づく2026/05/01のイベント情報です。内容や参加条件は公式情報で確認してください。",
          "startsAt": "2026-05-01T01:00:00.000Z",
          "endsAt": "2026-05-01T02:00:00.000Z",
          "sourceQuote": "スクール クーポン アクセス ONLINE SHOP お問い合わせ 03-6659-5843 NEWS MORE 2026/5/19 キッズクラス体験会開催！ 2026/5/1 2026年5月スケジュール 2026/3/1 【3月末まで延…",
          "extractionConfidence": "0.60",
          "reviewStatus": "pending",
          "decisionNote": "HEADROCK CLIMBING GYM 公式サイトからイベント候補を検出。日付候補は2026/05/01。Adminで開催日、内容、参加条件を確認してください。根拠抜粋: スクール クーポン アクセス ONLINE SHOP お問い合わせ 03-6659-5843 NEWS MORE 2026/5/19 キッズクラス体験会開催！ 2026/5/1 2026年5月スケジュール 2026/3/1 【3月末まで延…"
        },
        {
          "handle": "headrock-climbing",
          "sourceUrl": "https://headrock-climbing.com/#zac-2026-03-01-event-3",
          "sourceExternalId": "official-site:headrock-climbing:2026-03-01:event:3",
          "classification": "event",
          "title": "HEADROCK CLIMBING GYM 3月末まで延長",
          "summary": "HEADROCK CLIMBING GYMの公式情報に基づく2026/03/01のイベント情報です。内容や参加条件は公式情報で確認してください。",
          "startsAt": "2026-03-01T01:00:00.000Z",
          "endsAt": "2026-03-01T02:00:00.000Z",
          "sourceQuote": "HOP お問い合わせ 03-6659-5843 NEWS MORE 2026/5/19 キッズクラス体験会開催！ 2026/5/1 2026年5月スケジュール 2026/3/1 【3月末まで延長】始めたい人応援します！... 2026/3…",
          "extractionConfidence": "0.60",
          "reviewStatus": "pending",
          "decisionNote": "HEADROCK CLIMBING GYM 公式サイトからイベント候補を検出。日付候補は2026/03/01。Adminで開催日、内容、参加条件を確認してください。根拠抜粋: HOP お問い合わせ 03-6659-5843 NEWS MORE 2026/5/19 キッズクラス体験会開催！ 2026/5/1 2026年5月スケジュール 2026/3/1 【3月末まで延長】始めたい人応援します！... 2026/3…"
        }
      ]
    },
    {
      "handle": "limestone-climbing-club",
      "displayName": "LIMESTONE Climbing Club 公式サイト",
      "sourceUrl": "https://www.limestone.jp/",
      "sourceType": "official_site",
      "ok": true,
      "error": null,
      "failureCategory": null,
      "failureDetail": null,
      "candidates": [
        {
          "handle": "limestone-climbing-club",
          "sourceUrl": "https://www.limestone.jp/#zac-2026-05-12-competition-1",
          "sourceExternalId": "official-site:limestone-climbing-club:2026-05-12:competition:1",
          "classification": "competition",
          "title": "LIMESTONE Climbing Club 開店時間変更のお知らせ",
          "summary": "LIMESTONE Climbing Clubの公式情報に基づく2026/05/12のコンペ・大会情報です。開催日や申込方法は公式情報で確認してください。",
          "startsAt": "2026-05-12T01:00:00.000Z",
          "endsAt": "2026-05-12T02:00:00.000Z",
          "sourceQuote": "テップUPを目指す方へ 料金案内 よくあるご質問 INFORMATION アクセス ブログ search メニュー開閉 Youtube INFORMATION 2026/05/12 5/12(火)～5/17(日) 《旬の壁トライアル》開催…",
          "extractionConfidence": "0.60",
          "reviewStatus": "pending",
          "decisionNote": "LIMESTONE Climbing Club 公式サイトからコンペ・大会候補を検出。日付候補は2026/05/12。Adminで開催日、対象店舗、参加条件、申込要否を確認してください。根拠抜粋: テップUPを目指す方へ 料金案内 よくあるご質問 INFORMATION アクセス ブログ search メニュー開閉 Youtube INFORMATION 2026/05/12 5/12(火)～5/17(日) 《旬の壁トライアル》開催…"
        },
        {
          "handle": "limestone-climbing-club",
          "sourceUrl": "https://www.limestone.jp/#zac-2026-05-12-competition-2",
          "sourceExternalId": "official-site:limestone-climbing-club:2026-05-12:competition:2",
          "classification": "competition",
          "title": "LIMESTONE Climbing Club 開店時間変更のお知らせ",
          "summary": "LIMESTONE Climbing Clubの公式情報に基づく2026/05/12のコンペ・大会情報です。開催日や申込方法は公式情報で確認してください。",
          "startsAt": "2026-05-12T01:00:00.000Z",
          "endsAt": "2026-05-12T02:00:00.000Z",
          "sourceQuote": "料金案内 よくあるご質問 INFORMATION アクセス ブログ search メニュー開閉 Youtube INFORMATION 2026/05/12 5/12(火)～5/17(日) 《旬の壁トライアル》開催中！ 2026/05/0…",
          "extractionConfidence": "0.60",
          "reviewStatus": "pending",
          "decisionNote": "LIMESTONE Climbing Club 公式サイトからコンペ・大会候補を検出。日付候補は2026/05/12。Adminで開催日、対象店舗、参加条件、申込要否を確認してください。根拠抜粋: 料金案内 よくあるご質問 INFORMATION アクセス ブログ search メニュー開閉 Youtube INFORMATION 2026/05/12 5/12(火)～5/17(日) 《旬の壁トライアル》開催中！ 2026/05/0…"
        },
        {
          "handle": "limestone-climbing-club",
          "sourceUrl": "https://www.limestone.jp/#zac-2026-05-17-competition-3",
          "sourceExternalId": "official-site:limestone-climbing-club:2026-05-17:competition:3",
          "classification": "competition",
          "title": "LIMESTONE Climbing Club 開店時間変更のお知らせ",
          "summary": "LIMESTONE Climbing Clubの公式情報に基づく2026/05/17のコンペ・大会情報です。開催日や申込方法は公式情報で確認してください。",
          "startsAt": "2026-05-17T01:00:00.000Z",
          "endsAt": "2026-05-17T02:00:00.000Z",
          "sourceQuote": "あるご質問 INFORMATION アクセス ブログ search メニュー開閉 Youtube INFORMATION 2026/05/12 5/12(火)～5/17(日) 《旬の壁トライアル》開催中！ 2026/05/05 5月🎏旬…",
          "extractionConfidence": "0.60",
          "reviewStatus": "pending",
          "decisionNote": "LIMESTONE Climbing Club 公式サイトからコンペ・大会候補を検出。日付候補は2026/05/17。Adminで開催日、対象店舗、参加条件、申込要否を確認してください。根拠抜粋: あるご質問 INFORMATION アクセス ブログ search メニュー開閉 Youtube INFORMATION 2026/05/12 5/12(火)～5/17(日) 《旬の壁トライアル》開催中！ 2026/05/05 5月🎏旬…"
        }
      ]
    },
    {
      "handle": "lutra-lutra",
      "displayName": "Lutra Lutra 公式サイト",
      "sourceUrl": "https://www.lutra-lutra.com/",
      "sourceType": "official_site",
      "ok": true,
      "error": null,
      "failureCategory": null,
      "failureDetail": null,
      "candidates": [
        {
          "handle": "lutra-lutra",
          "sourceUrl": "https://www.lutra-lutra.com/#zac-2026-03-31-competition-1",
          "sourceExternalId": "official-site:lutra-lutra:2026-03-31:competition:1",
          "classification": "competition",
          "title": "Lutra Lutra 03/31 コンペ",
          "summary": "Lutra Lutraの公式情報に基づく2026/03/31のコンペ・大会情報です。開催日や申込方法は公式情報で確認してください。",
          "startsAt": "2026-03-31T01:00:00.000Z",
          "endsAt": "2026-03-31T02:00:00.000Z",
          "sourceQuote": "\udf3b大ゴッホ展とTHEWALL合宿🌻 茨城生まれ、足立区育ち、サウナ好きなやつはだいたいトモダチ🎵てんちょーです福島美術館で開幕中の大ゴッホ展に突撃です💨 2026.03.31 08:27 ジム 観光 お風呂 ✨６面リニューアル✨今月…",
          "extractionConfidence": "0.60",
          "reviewStatus": "pending",
          "decisionNote": "Lutra Lutra 公式サイトからコンペ・大会候補を検出。日付候補は2026/03/31。Adminで開催日、対象店舗、参加条件、申込要否を確認してください。根拠抜粋: \udf3b大ゴッホ展とTHEWALL合宿🌻 茨城生まれ、足立区育ち、サウナ好きなやつはだいたいトモダチ🎵てんちょーです福島美術館で開幕中の大ゴッホ展に突撃です💨 2026.03.31 08:27 ジム 観光 お風呂 ✨６面リニューアル✨今月…"
        }
      ]
    },
    {
      "handle": "monolithe-bouldering-gym",
      "displayName": "Monolithe Bouldering Gym 公式サイト",
      "sourceUrl": "https://www.boulderinggym.jp/",
      "sourceType": "official_site",
      "ok": true,
      "error": null,
      "failureCategory": null,
      "failureDetail": null,
      "candidates": []
    },
    {
      "handle": "noborock-ikebukuro",
      "displayName": "NOBOROCK 池袋店 公式サイト",
      "sourceUrl": "https://noborock-climbing.com/program/ikebukuro/",
      "sourceType": "official_site",
      "ok": true,
      "error": null,
      "failureCategory": null,
      "failureDetail": null,
      "candidates": [
        {
          "handle": "noborock-ikebukuro",
          "sourceUrl": "https://noborock-climbing.com/program/ikebukuro/#zac-2026-05-08-route_set-1",
          "sourceExternalId": "official-site:noborock-ikebukuro:2026-05-08:route_set:1",
          "classification": "route_set",
          "title": "NOBOROCK 池袋店 2026/05/08 セット",
          "summary": "NOBOROCK 池袋店の公式情報に基づく2026/05/08のセット・ホールド替え情報です。対象エリアや利用制限は公式情報で確認してください。",
          "startsAt": "2026-05-08T01:00:00.000Z",
          "endsAt": "2026-05-08T02:00:00.000Z",
          "sourceQuote": "浅草店 高田馬場店 渋谷店 池袋店 町田店 溝ノ口店 大宮店 カレンダー 撮影について ホーム 店舗案内 店舗 池袋店 店舗 池袋店 お知らせ 【ルートセット】 5/8 ルートセット完了！ 6/7(日) 17:00 close 6/8(月…",
          "extractionConfidence": "0.60",
          "reviewStatus": "pending",
          "decisionNote": "NOBOROCK 池袋店 公式サイトからセット・ホールド替え候補を検出。日付候補は2026/05/08。Adminで対象エリア、作業期間、利用制限を確認してください。根拠抜粋: 浅草店 高田馬場店 渋谷店 池袋店 町田店 溝ノ口店 大宮店 カレンダー 撮影について ホーム 店舗案内 店舗 池袋店 店舗 池袋店 お知らせ 【ルートセット】 5/8 ルートセット完了！ 6/7(日) 17:00 close 6/8(月…"
        },
        {
          "handle": "noborock-ikebukuro",
          "sourceUrl": "https://noborock-climbing.com/program/ikebukuro/#zac-2026-06-07-route_set-2",
          "sourceExternalId": "official-site:noborock-ikebukuro:2026-06-07:route_set:2",
          "classification": "route_set",
          "title": "NOBOROCK 池袋店 2026/06/07 セット",
          "summary": "NOBOROCK 池袋店の公式情報に基づく2026/06/07のセット・ホールド替え情報です。対象エリアや利用制限は公式情報で確認してください。",
          "startsAt": "2026-06-07T01:00:00.000Z",
          "endsAt": "2026-06-07T02:00:00.000Z",
          "sourceQuote": "池袋店 町田店 溝ノ口店 大宮店 カレンダー 撮影について ホーム 店舗案内 店舗 池袋店 店舗 池袋店 お知らせ 【ルートセット】 5/8 ルートセット完了！ 6/7(日) 17:00 close 6/8(月) close 6/9(火)…",
          "extractionConfidence": "0.60",
          "reviewStatus": "pending",
          "decisionNote": "NOBOROCK 池袋店 公式サイトからセット・ホールド替え候補を検出。日付候補は2026/06/07。Adminで対象エリア、作業期間、利用制限を確認してください。根拠抜粋: 池袋店 町田店 溝ノ口店 大宮店 カレンダー 撮影について ホーム 店舗案内 店舗 池袋店 店舗 池袋店 お知らせ 【ルートセット】 5/8 ルートセット完了！ 6/7(日) 17:00 close 6/8(月) close 6/9(火)…"
        },
        {
          "handle": "noborock-ikebukuro",
          "sourceUrl": "https://noborock-climbing.com/program/ikebukuro/#zac-2026-06-08-route_set-3",
          "sourceExternalId": "official-site:noborock-ikebukuro:2026-06-08:route_set:3",
          "classification": "route_set",
          "title": "NOBOROCK 池袋店 2026/06/08 セット",
          "summary": "NOBOROCK 池袋店の公式情報に基づく2026/06/08のセット・ホールド替え情報です。対象エリアや利用制限は公式情報で確認してください。",
          "startsAt": "2026-06-08T01:00:00.000Z",
          "endsAt": "2026-06-08T02:00:00.000Z",
          "sourceQuote": "ンダー 撮影について ホーム 店舗案内 店舗 池袋店 店舗 池袋店 お知らせ 【ルートセット】 5/8 ルートセット完了！ 6/7(日) 17:00 close 6/8(月) close 6/9(火) 18:30 open! 施設案内 池…",
          "extractionConfidence": "0.60",
          "reviewStatus": "pending",
          "decisionNote": "NOBOROCK 池袋店 公式サイトからセット・ホールド替え候補を検出。日付候補は2026/06/08。Adminで対象エリア、作業期間、利用制限を確認してください。根拠抜粋: ンダー 撮影について ホーム 店舗案内 店舗 池袋店 店舗 池袋店 お知らせ 【ルートセット】 5/8 ルートセット完了！ 6/7(日) 17:00 close 6/8(月) close 6/9(火) 18:30 open! 施設案内 池…"
        }
      ]
    }
  ]
}
